<Signature xmlns="http://www.w3.org/2000/09/xmldsig#" Id="DistributorSignature">
<SignedInfo>
<CanonicalizationMethod Algorithm="http://www.w3.org/2001/10/xml-exc-c14n#"></CanonicalizationMethod>
<SignatureMethod Algorithm="http://www.w3.org/2001/04/xmldsig-more#rsa-sha256"></SignatureMethod>
<Reference URI="app.js">
<DigestMethod Algorithm="http://www.w3.org/2001/04/xmlenc#sha256"></DigestMethod>
<DigestValue>SkSx5K7aZAdI7Z0JC5t48VPc+hPvE26FWLLCK7Ijol4=</DigestValue>
</Reference>
<Reference URI="author-signature.xml">
<DigestMethod Algorithm="http://www.w3.org/2001/04/xmlenc#sha256"></DigestMethod>
<DigestValue>syiaGzDAkBCGPos5CWEy5hMxelxLqPGj8IphF7qyOnM=</DigestValue>
</Reference>
<Reference URI="config.xml">
<DigestMethod Algorithm="http://www.w3.org/2001/04/xmlenc#sha256"></DigestMethod>
<DigestValue>YP0DRgDnUrEEqMeMBy7h/e1t2b3GYWbAWbrt27ippPc=</DigestValue>
</Reference>
<Reference URI="css%2Fstyle.css">
<DigestMethod Algorithm="http://www.w3.org/2001/04/xmlenc#sha256"></DigestMethod>
<DigestValue>0/mhZV4kwFnSzCSp45AhFjWaQnaie61uW8VeXioOLQg=</DigestValue>
</Reference>
<Reference URI="icon.png">
<DigestMethod Algorithm="http://www.w3.org/2001/04/xmlenc#sha256"></DigestMethod>
<DigestValue>vPjxjOppORd6hn9Bw4sh06gqtDoJzoFbV/8e9FyIdvk=</DigestValue>
</Reference>
<Reference URI="index.html">
<DigestMethod Algorithm="http://www.w3.org/2001/04/xmlenc#sha256"></DigestMethod>
<DigestValue>e+gZsVKHdPfbQI/a6HiQNMTMmCoVij6WjrrA4zXg2CM=</DigestValue>
</Reference>
<Reference URI="js%2Fcircle-helper.js">
<DigestMethod Algorithm="http://www.w3.org/2001/04/xmlenc#sha256"></DigestMethod>
<DigestValue>/IdbzbWyjh09Fek1Kwa7pS/Y+jFGbm4R5IVow3CzRIQ=</DigestValue>
</Reference>
<Reference URI="kisspng-computer-icons-favicon-latching-relay-light-switch-icons-no-attribution-5ab09d7dad1d72.3514324515215240937091.jpg">
<DigestMethod Algorithm="http://www.w3.org/2001/04/xmlenc#sha256"></DigestMethod>
<DigestValue>WiFt8gcF7xcrX3HzFgt/A3lu+rlIieLY5ddRDyhKD/A=</DigestValue>
</Reference>
<Reference URI="lib%2Ftau%2FLICENSE.Flora">
<DigestMethod Algorithm="http://www.w3.org/2001/04/xmlenc#sha256"></DigestMethod>
<DigestValue>R4988xI3tkQMAcLGLOROY5Wp8YTDrI0X90uMvrydtQw=</DigestValue>
</Reference>
<Reference URI="lib%2Ftau%2FVERSION">
<DigestMethod Algorithm="http://www.w3.org/2001/04/xmlenc#sha256"></DigestMethod>
<DigestValue>+LTBc0txAW6nTb21lilgo5YWFfM3fd9YXJVs/Tl7HW0=</DigestValue>
</Reference>
<Reference URI="lib%2Ftau%2Fwearable%2Fjs%2Ftau.js">
<DigestMethod Algorithm="http://www.w3.org/2001/04/xmlenc#sha256"></DigestMethod>
<DigestValue>aNzeR1lrF5WVuEAXvLkkPTF9mkfxXLWSXRnGgnXnIhY=</DigestValue>
</Reference>
<Reference URI="lib%2Ftau%2Fwearable%2Fjs%2Ftau.min.js">
<DigestMethod Algorithm="http://www.w3.org/2001/04/xmlenc#sha256"></DigestMethod>
<DigestValue>DFfx1OEP74kwXJcM2tWnqjSYuXzB7C4qEIQJRjW2Vcc=</DigestValue>
</Reference>
<Reference URI="lib%2Ftau%2Fwearable%2Ftheme%2Fblue%2Fimages%2FActionbar%2Fb_more_option.png">
<DigestMethod Algorithm="http://www.w3.org/2001/04/xmlenc#sha256"></DigestMethod>
<DigestValue>kc1wJhzruwjgLS1vfPkmSQHz67R48K6bh8LpwjDuE+M=</DigestValue>
</Reference>
<Reference URI="lib%2Ftau%2Fwearable%2Ftheme%2Fblue%2Fimages%2FActionbar%2Ftw_ic_menu_moreoverflow_holo_dark.png">
<DigestMethod Algorithm="http://www.w3.org/2001/04/xmlenc#sha256"></DigestMethod>
<DigestValue>qkbuZm3KXZNobT9lxfhl6LdiG8ERnIdYMArm45mDI3g=</DigestValue>
</Reference>
<Reference URI="lib%2Ftau%2Fwearable%2Ftheme%2Fblue%2Fimages%2FCommon%2Fb_rotary_selector_center_pointer.png">
<DigestMethod Algorithm="http://www.w3.org/2001/04/xmlenc#sha256"></DigestMethod>
<DigestValue>jCnR9UxCYfKDwEXOuyk64OPrdV6jMH2gnTv7xxpT8pI=</DigestValue>
</Reference>
<Reference URI="lib%2Ftau%2Fwearable%2Ftheme%2Fblue%2Fimages%2FCommon%2Fmasking_bg.png">
<DigestMethod Algorithm="http://www.w3.org/2001/04/xmlenc#sha256"></DigestMethod>
<DigestValue>xg0blL/qm/PlWrv4gh9D5VbFduHT4mEgGpNRugTHpbo=</DigestValue>
</Reference>
<Reference URI="lib%2Ftau%2Fwearable%2Ftheme%2Fblue%2Fimages%2FController_icon%2FCheck%2Fref_btn_check_holo_dark.png">
<DigestMethod Algorithm="http://www.w3.org/2001/04/xmlenc#sha256"></DigestMethod>
<DigestValue>NWtT1Dj4doBFgGMhL/7RjdD1FG12IcjqwujPGK1PAmY=</DigestValue>
</Reference>
<Reference URI="lib%2Ftau%2Fwearable%2Ftheme%2Fblue%2Fimages%2FController_icon%2FCheck%2Ftw_btn_check_bg_holo_dark.png">
<DigestMethod Algorithm="http://www.w3.org/2001/04/xmlenc#sha256"></DigestMethod>
<DigestValue>ukc3arzEQ6qP3AHgftAkBtwZyuc0q3JNL2lro88eYak=</DigestValue>
</Reference>
<Reference URI="lib%2Ftau%2Fwearable%2Ftheme%2Fblue%2Fimages%2FController_icon%2FCheck%2Ftw_btn_check_holo_dark.png">
<DigestMethod Algorithm="http://www.w3.org/2001/04/xmlenc#sha256"></DigestMethod>
<DigestValue>t2riLxtAI1RWhbl6os4UkxBGczwhJFdUFF7DNcka9zM=</DigestValue>
</Reference>
<Reference URI="lib%2Ftau%2Fwearable%2Ftheme%2Fblue%2Fimages%2FController_icon%2FOn_Off%2Ftw_btn_control_bg_holo_dark.png">
<DigestMethod Algorithm="http://www.w3.org/2001/04/xmlenc#sha256"></DigestMethod>
<DigestValue>GbaaRiAZjvqf/AcpgD940qqHEcseOMFWnu8ham//jTg=</DigestValue>
</Reference>
<Reference URI="lib%2Ftau%2Fwearable%2Ftheme%2Fblue%2Fimages%2FController_icon%2FOn_Off%2Ftw_btn_control_off_holo_dark.png">
<DigestMethod Algorithm="http://www.w3.org/2001/04/xmlenc#sha256"></DigestMethod>
<DigestValue>N06Ed3Ihxxo2MldtVQKRq0qYl1eRbuo0zEe2medE1J0=</DigestValue>
</Reference>
<Reference URI="lib%2Ftau%2Fwearable%2Ftheme%2Fblue%2Fimages%2FController_icon%2FOn_Off%2Ftw_btn_control_on_holo_dark.png">
<DigestMethod Algorithm="http://www.w3.org/2001/04/xmlenc#sha256"></DigestMethod>
<DigestValue>ph0ljcHGNXlJO1dPAiAQgDpRH3+mbMZZ3Ega7lNW/cw=</DigestValue>
</Reference>
<Reference URI="lib%2Ftau%2Fwearable%2Ftheme%2Fblue%2Fimages%2FController_icon%2FRadio%2Ftw_btn_radio_holo_dark.png">
<DigestMethod Algorithm="http://www.w3.org/2001/04/xmlenc#sha256"></DigestMethod>
<DigestValue>3i13zlE5UUPepY9sbRmsu3oxYmIBCpM9hwL0YyiVaEI=</DigestValue>
</Reference>
<Reference URI="lib%2Ftau%2Fwearable%2Ftheme%2Fblue%2Fimages%2FController_icon%2Ftoggle_changeable.png">
<DigestMethod Algorithm="http://www.w3.org/2001/04/xmlenc#sha256"></DigestMethod>
<DigestValue>BzK0UNVeSZCohwIBfIkqCru85HE/86q/2MZUEQJWcoU=</DigestValue>
</Reference>
<Reference URI="lib%2Ftau%2Fwearable%2Ftheme%2Fblue%2Fimages%2FController_icon%2Ftw_btn_check_holo_dark.png">
<DigestMethod Algorithm="http://www.w3.org/2001/04/xmlenc#sha256"></DigestMethod>
<DigestValue>qFC8fOl6Tg7LrLrT62RSQLKSr3GP6O2UwjnG9s7DAck=</DigestValue>
</Reference>
<Reference URI="lib%2Ftau%2Fwearable%2Ftheme%2Fblue%2Fimages%2FController_icon%2Ftw_btn_checkbox_holo_dark.png">
<DigestMethod Algorithm="http://www.w3.org/2001/04/xmlenc#sha256"></DigestMethod>
<DigestValue>ddihq2E6gV6+g48CtlRBvDFnKx97KWUJxoNr8SQ7sUQ=</DigestValue>
</Reference>
<Reference URI="lib%2Ftau%2Fwearable%2Ftheme%2Fblue%2Fimages%2FController_icon%2Ftw_btn_checkbox_line_holo_dark.png">
<DigestMethod Algorithm="http://www.w3.org/2001/04/xmlenc#sha256"></DigestMethod>
<DigestValue>elPeRLEot+b5h79G5sudnUNkc6GhAyye82uL2cn9xxc=</DigestValue>
</Reference>
<Reference URI="lib%2Ftau%2Fwearable%2Ftheme%2Fblue%2Fimages%2FController_icon%2Ftw_btn_radio_holo_dark.png">
<DigestMethod Algorithm="http://www.w3.org/2001/04/xmlenc#sha256"></DigestMethod>
<DigestValue>SYKDGM5OUHfYf65YinTD2vzNNMNUjKEABJaxy/68hv4=</DigestValue>
</Reference>
<Reference URI="lib%2Ftau%2Fwearable%2Ftheme%2Fblue%2Fimages%2FController_icon%2Ftw_btn_radiobox_holo_dark.png">
<DigestMethod Algorithm="http://www.w3.org/2001/04/xmlenc#sha256"></DigestMethod>
<DigestValue>nwK+t+eTDiAjgXRMhNpbO52ccNtX1T8to7iUEfvtEw0=</DigestValue>
</Reference>
<Reference URI="lib%2Ftau%2Fwearable%2Ftheme%2Fblue%2Fimages%2FController_icon%2Ftw_btn_radiobox_line.png">
<DigestMethod Algorithm="http://www.w3.org/2001/04/xmlenc#sha256"></DigestMethod>
<DigestValue>JXfJFsytb7Ca9bHn2mZ7J5UVde6gr5WIQWFARUEbSAI=</DigestValue>
</Reference>
<Reference URI="lib%2Ftau%2Fwearable%2Ftheme%2Fblue%2Fimages%2FIndicator%2Fb_fast_scroll_rollover_bg.png">
<DigestMethod Algorithm="http://www.w3.org/2001/04/xmlenc#sha256"></DigestMethod>
<DigestValue>BdM1nG2OXAGZ/Jjerne40hr4z+CUVQDaGGDC9NKHbJ4=</DigestValue>
</Reference>
<Reference URI="lib%2Ftau%2Fwearable%2Ftheme%2Fblue%2Fimages%2FIndicator%2Fb_index_scroll_bg.png">
<DigestMethod Algorithm="http://www.w3.org/2001/04/xmlenc#sha256"></DigestMethod>
<DigestValue>G1lZylmCqAW+9pxtAqkRcvWmAaqrhmKmFNQ6S+Gfofo=</DigestValue>
</Reference>
<Reference URI="lib%2Ftau%2Fwearable%2Ftheme%2Fblue%2Fimages%2FIndicator%2Flist_scroll_triggle.png">
<DigestMethod Algorithm="http://www.w3.org/2001/04/xmlenc#sha256"></DigestMethod>
<DigestValue>7GQe3ejeCKtt6U+41MqwJ8q3SaU7cwmfF1sFnFygjCw=</DigestValue>
</Reference>
<Reference URI="lib%2Ftau%2Fwearable%2Ftheme%2Fblue%2Fimages%2FList%2Fb_body_edge_shadow.png">
<DigestMethod Algorithm="http://www.w3.org/2001/04/xmlenc#sha256"></DigestMethod>
<DigestValue>xUE9SahpNHNokTSvhfV04BMB0Mdz4wsHy22HYi+93B4=</DigestValue>
</Reference>
<Reference URI="lib%2Ftau%2Fwearable%2Ftheme%2Fblue%2Fimages%2FList%2Fb_list_focus_bg_108.png">
<DigestMethod Algorithm="http://www.w3.org/2001/04/xmlenc#sha256"></DigestMethod>
<DigestValue>Ds+e1ERJ7fKikfUF7LTSOFWaGS08JNA/R1xFTPfyGxY=</DigestValue>
</Reference>
<Reference URI="lib%2Ftau%2Fwearable%2Ftheme%2Fblue%2Fimages%2FPopup%2Fb_popup_edge_inner_glow.png">
<DigestMethod Algorithm="http://www.w3.org/2001/04/xmlenc#sha256"></DigestMethod>
<DigestValue>SAnFR0QqrmaF1Sq9WO6N22n4KCuOr0yiCxSelMuIlIo=</DigestValue>
</Reference>
<Reference URI="lib%2Ftau%2Fwearable%2Ftheme%2Fblue%2Fimages%2FPopup%2Fb_popup_edge_shadow.png">
<DigestMethod Algorithm="http://www.w3.org/2001/04/xmlenc#sha256"></DigestMethod>
<DigestValue>spXDbatBHTzSFR4N03w93hLrVybuw/XRjZAfneskshI=</DigestValue>
</Reference>
<Reference URI="lib%2Ftau%2Fwearable%2Ftheme%2Fblue%2Fimages%2FPopup%2Ftoast_check.png">
<DigestMethod Algorithm="http://www.w3.org/2001/04/xmlenc#sha256"></DigestMethod>
<DigestValue>l7tDb2GpWcNj93JU9VgQbbDgqEtDA7bdufKK12uMkPs=</DigestValue>
</Reference>
<Reference URI="lib%2Ftau%2Fwearable%2Ftheme%2Fblue%2Fimages%2FPopup%2Ftw_popup_bg.png">
<DigestMethod Algorithm="http://www.w3.org/2001/04/xmlenc#sha256"></DigestMethod>
<DigestValue>TphpTsohWyWK9j+2DXpOyvJSydRMq2Av5B0otjA9f9I=</DigestValue>
</Reference>
<Reference URI="lib%2Ftau%2Fwearable%2Ftheme%2Fblue%2Fimages%2FPopup%2Ftw_popup_bg_cover.png">
<DigestMethod Algorithm="http://www.w3.org/2001/04/xmlenc#sha256"></DigestMethod>
<DigestValue>vqXi7pK9urSnMFrdVlcc8IFvLcUduAMNIIgbnFvQc4A=</DigestValue>
</Reference>
<Reference URI="lib%2Ftau%2Fwearable%2Ftheme%2Fblue%2Fimages%2FPopup%2Ftw_toast_popup_bg.png">
<DigestMethod Algorithm="http://www.w3.org/2001/04/xmlenc#sha256"></DigestMethod>
<DigestValue>HQr3u9+djLy7CqBURR3qMnfvWxQRk+7KsyluA9KadzQ=</DigestValue>
</Reference>
<Reference URI="lib%2Ftau%2Fwearable%2Ftheme%2Fblue%2Fimages%2FPopup%2Ftw_toast_popup_bg_cover.png">
<DigestMethod Algorithm="http://www.w3.org/2001/04/xmlenc#sha256"></DigestMethod>
<DigestValue>PTz1Q9tb2jmV/h/NF704nw/+wpelkdig4FdwBoTkXIs=</DigestValue>
</Reference>
<Reference URI="lib%2Ftau%2Fwearable%2Ftheme%2Fblue%2Fimages%2FPopup%2Ftw_toast_popup_image_bg.png">
<DigestMethod Algorithm="http://www.w3.org/2001/04/xmlenc#sha256"></DigestMethod>
<DigestValue>3mjrv/wd1wI4zGsbemLKWEA3ARYZyZF/lx8XLE87aSQ=</DigestValue>
</Reference>
<Reference URI="lib%2Ftau%2Fwearable%2Ftheme%2Fblue%2Fimages%2FPopup%2Ftw_toast_popup_outline.png">
<DigestMethod Algorithm="http://www.w3.org/2001/04/xmlenc#sha256"></DigestMethod>
<DigestValue>mmYqlg9ixS5F00DUDkRiD8LJARxEPw7FwZpsINr4mwU=</DigestValue>
</Reference>
<Reference URI="lib%2Ftau%2Fwearable%2Ftheme%2Fblue%2Fimages%2FProcessing%2Fprocessingfull.png">
<DigestMethod Algorithm="http://www.w3.org/2001/04/xmlenc#sha256"></DigestMethod>
<DigestValue>inphL/shFiOknwr0eLnUc7CGLICqacQ36GidvhaEuJ4=</DigestValue>
</Reference>
<Reference URI="lib%2Ftau%2Fwearable%2Ftheme%2Fblue%2Fimages%2FProcessing%2Fprocessingsmall.png">
<DigestMethod Algorithm="http://www.w3.org/2001/04/xmlenc#sha256"></DigestMethod>
<DigestValue>C+hHn6OO+njwAy8GimgFpo+Owigwarpd0+/LdckPdjE=</DigestValue>
</Reference>
<Reference URI="lib%2Ftau%2Fwearable%2Ftheme%2Fblue%2Fimages%2FScroller%2Fbouncing_bottom_edge.png">
<DigestMethod Algorithm="http://www.w3.org/2001/04/xmlenc#sha256"></DigestMethod>
<DigestValue>EwF0JIrEoFCTVRThWK/aNHTfqUzl+oQ5xaoEVeCKakQ=</DigestValue>
</Reference>
<Reference URI="lib%2Ftau%2Fwearable%2Ftheme%2Fblue%2Fimages%2FScroller%2Fbouncing_bottom_glow.png">
<DigestMethod Algorithm="http://www.w3.org/2001/04/xmlenc#sha256"></DigestMethod>
<DigestValue>LBBYbeRMyt+BmcaK6OFcYxXCHatfcBy3WZmMEyeD494=</DigestValue>
</Reference>
<Reference URI="lib%2Ftau%2Fwearable%2Ftheme%2Fblue%2Fimages%2FScroller%2Fbouncing_circle_bottom_edge.png">
<DigestMethod Algorithm="http://www.w3.org/2001/04/xmlenc#sha256"></DigestMethod>
<DigestValue>4zpEk6E15paDUijxsmbabMs46TeXF4D7uOr8yXUBnl0=</DigestValue>
</Reference>
<Reference URI="lib%2Ftau%2Fwearable%2Ftheme%2Fblue%2Fimages%2FScroller%2Fbouncing_circle_bottom_glow.png">
<DigestMethod Algorithm="http://www.w3.org/2001/04/xmlenc#sha256"></DigestMethod>
<DigestValue>bcGdiIMylFL9ajYUoxh9Z+C/N1yfHdFvrvU4ocYLnoo=</DigestValue>
</Reference>
<Reference URI="lib%2Ftau%2Fwearable%2Ftheme%2Fblue%2Fimages%2FScroller%2Fbouncing_circle_left_edge.png">
<DigestMethod Algorithm="http://www.w3.org/2001/04/xmlenc#sha256"></DigestMethod>
<DigestValue>IcYY9gteu+cywMJ4ccIK+y8X7RNqxdxY5Xnb2rfW9zg=</DigestValue>
</Reference>
<Reference URI="lib%2Ftau%2Fwearable%2Ftheme%2Fblue%2Fimages%2FScroller%2Fbouncing_circle_left_glow.png">
<DigestMethod Algorithm="http://www.w3.org/2001/04/xmlenc#sha256"></DigestMethod>
<DigestValue>QJpek9IkYgeOa/DEUu0i+FJYw1G7pud0DErfVy6PtWI=</DigestValue>
</Reference>
<Reference URI="lib%2Ftau%2Fwearable%2Ftheme%2Fblue%2Fimages%2FScroller%2Fbouncing_circle_right_edge.png">
<DigestMethod Algorithm="http://www.w3.org/2001/04/xmlenc#sha256"></DigestMethod>
<DigestValue>UoL95mMLn9oWwZKXx4xfcKQUd5BZICIiNovQ0X59zpU=</DigestValue>
</Reference>
<Reference URI="lib%2Ftau%2Fwearable%2Ftheme%2Fblue%2Fimages%2FScroller%2Fbouncing_circle_right_glow.png">
<DigestMethod Algorithm="http://www.w3.org/2001/04/xmlenc#sha256"></DigestMethod>
<DigestValue>5KK+V+kpu/oD6Vd+6gE6JnOnJ29+ZI0ekabrdIX9dXs=</DigestValue>
</Reference>
<Reference URI="lib%2Ftau%2Fwearable%2Ftheme%2Fblue%2Fimages%2FScroller%2Fbouncing_left_edge.png">
<DigestMethod Algorithm="http://www.w3.org/2001/04/xmlenc#sha256"></DigestMethod>
<DigestValue>ezbad2I+Qvqq+HBtFj5fCR73B7u1OpaGp8LbvJiksx8=</DigestValue>
</Reference>
<Reference URI="lib%2Ftau%2Fwearable%2Ftheme%2Fblue%2Fimages%2FScroller%2Fbouncing_left_glow.png">
<DigestMethod Algorithm="http://www.w3.org/2001/04/xmlenc#sha256"></DigestMethod>
<DigestValue>i6payEnlv8vWHucju//UBssYNzmr3SES3nSuWDuJU6c=</DigestValue>
</Reference>
<Reference URI="lib%2Ftau%2Fwearable%2Ftheme%2Fblue%2Fimages%2FScroller%2Fbouncing_right_edge.png">
<DigestMethod Algorithm="http://www.w3.org/2001/04/xmlenc#sha256"></DigestMethod>
<DigestValue>wIF0gTMZq7piBZ9E/+l5UgyW9pSywlBedaETJbK5euE=</DigestValue>
</Reference>
<Reference URI="lib%2Ftau%2Fwearable%2Ftheme%2Fblue%2Fimages%2FScroller%2Fbouncing_right_glow.png">
<DigestMethod Algorithm="http://www.w3.org/2001/04/xmlenc#sha256"></DigestMethod>
<DigestValue>MZ/WXjPf0eoYefs4grYwm+dI4ehPs1D8ElGWv+wLcGk=</DigestValue>
</Reference>
<Reference URI="lib%2Ftau%2Fwearable%2Ftheme%2Fblue%2Fimages%2FScroller%2Fbouncing_top_edge.png">
<DigestMethod Algorithm="http://www.w3.org/2001/04/xmlenc#sha256"></DigestMethod>
<DigestValue>iEpyiqHYkrP3GQpul3S6C87yG+PyVBWzhrmvxzPf//0=</DigestValue>
</Reference>
<Reference URI="lib%2Ftau%2Fwearable%2Ftheme%2Fblue%2Fimages%2FScroller%2Fbouncing_top_glow.png">
<DigestMethod Algorithm="http://www.w3.org/2001/04/xmlenc#sha256"></DigestMethod>
<DigestValue>JmKqm+7nSe0dUkYRduPMoyyfc+Rg9gTVg2J7/pJq5F4=</DigestValue>
</Reference>
<Reference URI="lib%2Ftau%2Fwearable%2Ftheme%2Fblue%2Fimages%2FSwipelist%2Fb_logs_icon_actionbar_btn_msg_nor.png">
<DigestMethod Algorithm="http://www.w3.org/2001/04/xmlenc#sha256"></DigestMethod>
<DigestValue>f6LUaSBsZsugcSX2A3xcaHs+rghK2nFAneqNp7WbOMw=</DigestValue>
</Reference>
<Reference URI="lib%2Ftau%2Fwearable%2Ftheme%2Fblue%2Fimages%2FSwipelist%2Fb_logs_icon_body_btn_call_nor.png">
<DigestMethod Algorithm="http://www.w3.org/2001/04/xmlenc#sha256"></DigestMethod>
<DigestValue>fl7TG+5Mgf/y6KR8TdSEPcC/teaTrmRLm+lr9TSpOyg=</DigestValue>
</Reference>
<Reference URI="lib%2Ftau%2Fwearable%2Ftheme%2Fblue%2Fimages%2FTitle_bar%2Fb_detail_bg_cover.png">
<DigestMethod Algorithm="http://www.w3.org/2001/04/xmlenc#sha256"></DigestMethod>
<DigestValue>6MewTgCyy7oMiEvq3KkLoNcPwf7TXOAoEtF14XSlYoM=</DigestValue>
</Reference>
<Reference URI="lib%2Ftau%2Fwearable%2Ftheme%2Fblue%2Fimages%2Flistview%2Fb_list_focus_bg.png">
<DigestMethod Algorithm="http://www.w3.org/2001/04/xmlenc#sha256"></DigestMethod>
<DigestValue>Y2mvH98ij+UZgnL50uB1C7O0z7vycVJTo91w7YXqNL8=</DigestValue>
</Reference>
<Reference URI="lib%2Ftau%2Fwearable%2Ftheme%2Fblue%2Fimages%2Flistview%2Fb_list_focus_bg_ef.png">
<DigestMethod Algorithm="http://www.w3.org/2001/04/xmlenc#sha256"></DigestMethod>
<DigestValue>esp0LccF3OAwLTU/MP0HKKyDwKxOSL+W+r5CkeMRlFs=</DigestValue>
</Reference>
<Reference URI="lib%2Ftau%2Fwearable%2Ftheme%2Fblue%2Fimages%2Flistview%2Ftw_list_sub_line_left.png">
<DigestMethod Algorithm="http://www.w3.org/2001/04/xmlenc#sha256"></DigestMethod>
<DigestValue>shV08ijW9zUS7nWDPJJhii7sJ+I8PGnaiWIqM2eQupI=</DigestValue>
</Reference>
<Reference URI="lib%2Ftau%2Fwearable%2Ftheme%2Fblue%2Fimages%2Flistview%2Ftw_list_sub_line_right.png">
<DigestMethod Algorithm="http://www.w3.org/2001/04/xmlenc#sha256"></DigestMethod>
<DigestValue>5bj8yP8hzh1GCTNeAEUIiVshD964KCede5tOIlybtZY=</DigestValue>
</Reference>
<Reference URI="lib%2Ftau%2Fwearable%2Ftheme%2Fblue%2Ftau.css">
<DigestMethod Algorithm="http://www.w3.org/2001/04/xmlenc#sha256"></DigestMethod>
<DigestValue>TtVuteUo5uSKfc8FyqVEv2u+KeqXKRtfJ1gkPXoyMgI=</DigestValue>
</Reference>
<Reference URI="lib%2Ftau%2Fwearable%2Ftheme%2Fblue%2Ftau.min.css">
<DigestMethod Algorithm="http://www.w3.org/2001/04/xmlenc#sha256"></DigestMethod>
<DigestValue>nlqraPG4D/iUagIpoBeMNu6hxtPooUhsWr4K83m4tPg=</DigestValue>
</Reference>
<Reference URI="lib%2Ftau%2Fwearable%2Ftheme%2Fbrown%2Fimages%2FActionbar%2Fb_more_option.png">
<DigestMethod Algorithm="http://www.w3.org/2001/04/xmlenc#sha256"></DigestMethod>
<DigestValue>kc1wJhzruwjgLS1vfPkmSQHz67R48K6bh8LpwjDuE+M=</DigestValue>
</Reference>
<Reference URI="lib%2Ftau%2Fwearable%2Ftheme%2Fbrown%2Fimages%2FActionbar%2Ftw_ic_menu_moreoverflow_holo_dark.png">
<DigestMethod Algorithm="http://www.w3.org/2001/04/xmlenc#sha256"></DigestMethod>
<DigestValue>qkbuZm3KXZNobT9lxfhl6LdiG8ERnIdYMArm45mDI3g=</DigestValue>
</Reference>
<Reference URI="lib%2Ftau%2Fwearable%2Ftheme%2Fbrown%2Fimages%2FCommon%2Fb_rotary_selector_center_pointer.png">
<DigestMethod Algorithm="http://www.w3.org/2001/04/xmlenc#sha256"></DigestMethod>
<DigestValue>jCnR9UxCYfKDwEXOuyk64OPrdV6jMH2gnTv7xxpT8pI=</DigestValue>
</Reference>
<Reference URI="lib%2Ftau%2Fwearable%2Ftheme%2Fbrown%2Fimages%2FCommon%2Fmasking_bg.png">
<DigestMethod Algorithm="http://www.w3.org/2001/04/xmlenc#sha256"></DigestMethod>
<DigestValue>xg0blL/qm/PlWrv4gh9D5VbFduHT4mEgGpNRugTHpbo=</DigestValue>
</Reference>
<Reference URI="lib%2Ftau%2Fwearable%2Ftheme%2Fbrown%2Fimages%2FController_icon%2FCheck%2Fref_btn_check_holo_dark.png">
<DigestMethod Algorithm="http://www.w3.org/2001/04/xmlenc#sha256"></DigestMethod>
<DigestValue>NWtT1Dj4doBFgGMhL/7RjdD1FG12IcjqwujPGK1PAmY=</DigestValue>
</Reference>
<Reference URI="lib%2Ftau%2Fwearable%2Ftheme%2Fbrown%2Fimages%2FController_icon%2FCheck%2Ftw_btn_check_bg_holo_dark.png">
<DigestMethod Algorithm="http://www.w3.org/2001/04/xmlenc#sha256"></DigestMethod>
<DigestValue>ukc3arzEQ6qP3AHgftAkBtwZyuc0q3JNL2lro88eYak=</DigestValue>
</Reference>
<Reference URI="lib%2Ftau%2Fwearable%2Ftheme%2Fbrown%2Fimages%2FController_icon%2FCheck%2Ftw_btn_check_holo_dark.png">
<DigestMethod Algorithm="http://www.w3.org/2001/04/xmlenc#sha256"></DigestMethod>
<DigestValue>t2riLxtAI1RWhbl6os4UkxBGczwhJFdUFF7DNcka9zM=</DigestValue>
</Reference>
<Reference URI="lib%2Ftau%2Fwearable%2Ftheme%2Fbrown%2Fimages%2FController_icon%2FOn_Off%2Ftw_btn_control_bg_holo_dark.png">
<DigestMethod Algorithm="http://www.w3.org/2001/04/xmlenc#sha256"></DigestMethod>
<DigestValue>GbaaRiAZjvqf/AcpgD940qqHEcseOMFWnu8ham//jTg=</DigestValue>
</Reference>
<Reference URI="lib%2Ftau%2Fwearable%2Ftheme%2Fbrown%2Fimages%2FController_icon%2FOn_Off%2Ftw_btn_control_off_holo_dark.png">
<DigestMethod Algorithm="http://www.w3.org/2001/04/xmlenc#sha256"></DigestMethod>
<DigestValue>N06Ed3Ihxxo2MldtVQKRq0qYl1eRbuo0zEe2medE1J0=</DigestValue>
</Reference>
<Reference URI="lib%2Ftau%2Fwearable%2Ftheme%2Fbrown%2Fimages%2FController_icon%2FOn_Off%2Ftw_btn_control_on_holo_dark.png">
<DigestMethod Algorithm="http://www.w3.org/2001/04/xmlenc#sha256"></DigestMethod>
<DigestValue>ph0ljcHGNXlJO1dPAiAQgDpRH3+mbMZZ3Ega7lNW/cw=</DigestValue>
</Reference>
<Reference URI="lib%2Ftau%2Fwearable%2Ftheme%2Fbrown%2Fimages%2FController_icon%2FRadio%2Ftw_btn_radio_holo_dark.png">
<DigestMethod Algorithm="http://www.w3.org/2001/04/xmlenc#sha256"></DigestMethod>
<DigestValue>3i13zlE5UUPepY9sbRmsu3oxYmIBCpM9hwL0YyiVaEI=</DigestValue>
</Reference>
<Reference URI="lib%2Ftau%2Fwearable%2Ftheme%2Fbrown%2Fimages%2FController_icon%2Ftoggle_changeable.png">
<DigestMethod Algorithm="http://www.w3.org/2001/04/xmlenc#sha256"></DigestMethod>
<DigestValue>BzK0UNVeSZCohwIBfIkqCru85HE/86q/2MZUEQJWcoU=</DigestValue>
</Reference>
<Reference URI="lib%2Ftau%2Fwearable%2Ftheme%2Fbrown%2Fimages%2FController_icon%2Ftw_btn_check_holo_dark.png">
<DigestMethod Algorithm="http://www.w3.org/2001/04/xmlenc#sha256"></DigestMethod>
<DigestValue>qFC8fOl6Tg7LrLrT62RSQLKSr3GP6O2UwjnG9s7DAck=</DigestValue>
</Reference>
<Reference URI="lib%2Ftau%2Fwearable%2Ftheme%2Fbrown%2Fimages%2FController_icon%2Ftw_btn_checkbox_holo_dark.png">
<DigestMethod Algorithm="http://www.w3.org/2001/04/xmlenc#sha256"></DigestMethod>
<DigestValue>ddihq2E6gV6+g48CtlRBvDFnKx97KWUJxoNr8SQ7sUQ=</DigestValue>
</Reference>
<Reference URI="lib%2Ftau%2Fwearable%2Ftheme%2Fbrown%2Fimages%2FController_icon%2Ftw_btn_checkbox_line_holo_dark.png">
<DigestMethod Algorithm="http://www.w3.org/2001/04/xmlenc#sha256"></DigestMethod>
<DigestValue>elPeRLEot+b5h79G5sudnUNkc6GhAyye82uL2cn9xxc=</DigestValue>
</Reference>
<Reference URI="lib%2Ftau%2Fwearable%2Ftheme%2Fbrown%2Fimages%2FController_icon%2Ftw_btn_radio_holo_dark.png">
<DigestMethod Algorithm="http://www.w3.org/2001/04/xmlenc#sha256"></DigestMethod>
<DigestValue>SYKDGM5OUHfYf65YinTD2vzNNMNUjKEABJaxy/68hv4=</DigestValue>
</Reference>
<Reference URI="lib%2Ftau%2Fwearable%2Ftheme%2Fbrown%2Fimages%2FController_icon%2Ftw_btn_radiobox_holo_dark.png">
<DigestMethod Algorithm="http://www.w3.org/2001/04/xmlenc#sha256"></DigestMethod>
<DigestValue>nwK+t+eTDiAjgXRMhNpbO52ccNtX1T8to7iUEfvtEw0=</DigestValue>
</Reference>
<Reference URI="lib%2Ftau%2Fwearable%2Ftheme%2Fbrown%2Fimages%2FController_icon%2Ftw_btn_radiobox_line.png">
<DigestMethod Algorithm="http://www.w3.org/2001/04/xmlenc#sha256"></DigestMethod>
<DigestValue>JXfJFsytb7Ca9bHn2mZ7J5UVde6gr5WIQWFARUEbSAI=</DigestValue>
</Reference>
<Reference URI="lib%2Ftau%2Fwearable%2Ftheme%2Fbrown%2Fimages%2FIndicator%2Fb_fast_scroll_rollover_bg.png">
<DigestMethod Algorithm="http://www.w3.org/2001/04/xmlenc#sha256"></DigestMethod>
<DigestValue>BdM1nG2OXAGZ/Jjerne40hr4z+CUVQDaGGDC9NKHbJ4=</DigestValue>
</Reference>
<Reference URI="lib%2Ftau%2Fwearable%2Ftheme%2Fbrown%2Fimages%2FIndicator%2Fb_index_scroll_bg.png">
<DigestMethod Algorithm="http://www.w3.org/2001/04/xmlenc#sha256"></DigestMethod>
<DigestValue>G1lZylmCqAW+9pxtAqkRcvWmAaqrhmKmFNQ6S+Gfofo=</DigestValue>
</Reference>
<Reference URI="lib%2Ftau%2Fwearable%2Ftheme%2Fbrown%2Fimages%2FIndicator%2Flist_scroll_triggle.png">
<DigestMethod Algorithm="http://www.w3.org/2001/04/xmlenc#sha256"></DigestMethod>
<DigestValue>7GQe3ejeCKtt6U+41MqwJ8q3SaU7cwmfF1sFnFygjCw=</DigestValue>
</Reference>
<Reference URI="lib%2Ftau%2Fwearable%2Ftheme%2Fbrown%2Fimages%2FList%2Fb_body_edge_shadow.png">
<DigestMethod Algorithm="http://www.w3.org/2001/04/xmlenc#sha256"></DigestMethod>
<DigestValue>xUE9SahpNHNokTSvhfV04BMB0Mdz4wsHy22HYi+93B4=</DigestValue>
</Reference>
<Reference URI="lib%2Ftau%2Fwearable%2Ftheme%2Fbrown%2Fimages%2FList%2Fb_list_focus_bg_108.png">
<DigestMethod Algorithm="http://www.w3.org/2001/04/xmlenc#sha256"></DigestMethod>
<DigestValue>Ds+e1ERJ7fKikfUF7LTSOFWaGS08JNA/R1xFTPfyGxY=</DigestValue>
</Reference>
<Reference URI="lib%2Ftau%2Fwearable%2Ftheme%2Fbrown%2Fimages%2FPopup%2Fb_popup_edge_inner_glow.png">
<DigestMethod Algorithm="http://www.w3.org/2001/04/xmlenc#sha256"></DigestMethod>
<DigestValue>SAnFR0QqrmaF1Sq9WO6N22n4KCuOr0yiCxSelMuIlIo=</DigestValue>
</Reference>
<Reference URI="lib%2Ftau%2Fwearable%2Ftheme%2Fbrown%2Fimages%2FPopup%2Fb_popup_edge_shadow.png">
<DigestMethod Algorithm="http://www.w3.org/2001/04/xmlenc#sha256"></DigestMethod>
<DigestValue>spXDbatBHTzSFR4N03w93hLrVybuw/XRjZAfneskshI=</DigestValue>
</Reference>
<Reference URI="lib%2Ftau%2Fwearable%2Ftheme%2Fbrown%2Fimages%2FPopup%2Ftoast_check.png">
<DigestMethod Algorithm="http://www.w3.org/2001/04/xmlenc#sha256"></DigestMethod>
<DigestValue>l7tDb2GpWcNj93JU9VgQbbDgqEtDA7bdufKK12uMkPs=</DigestValue>
</Reference>
<Reference URI="lib%2Ftau%2Fwearable%2Ftheme%2Fbrown%2Fimages%2FPopup%2Ftw_popup_bg.png">
<DigestMethod Algorithm="http://www.w3.org/2001/04/xmlenc#sha256"></DigestMethod>
<DigestValue>TphpTsohWyWK9j+2DXpOyvJSydRMq2Av5B0otjA9f9I=</DigestValue>
</Reference>
<Reference URI="lib%2Ftau%2Fwearable%2Ftheme%2Fbrown%2Fimages%2FPopup%2Ftw_popup_bg_cover.png">
<DigestMethod Algorithm="http://www.w3.org/2001/04/xmlenc#sha256"></DigestMethod>
<DigestValue>vqXi7pK9urSnMFrdVlcc8IFvLcUduAMNIIgbnFvQc4A=</DigestValue>
</Reference>
<Reference URI="lib%2Ftau%2Fwearable%2Ftheme%2Fbrown%2Fimages%2FPopup%2Ftw_toast_popup_bg.png">
<DigestMethod Algorithm="http://www.w3.org/2001/04/xmlenc#sha256"></DigestMethod>
<DigestValue>HQr3u9+djLy7CqBURR3qMnfvWxQRk+7KsyluA9KadzQ=</DigestValue>
</Reference>
<Reference URI="lib%2Ftau%2Fwearable%2Ftheme%2Fbrown%2Fimages%2FPopup%2Ftw_toast_popup_bg_cover.png">
<DigestMethod Algorithm="http://www.w3.org/2001/04/xmlenc#sha256"></DigestMethod>
<DigestValue>PTz1Q9tb2jmV/h/NF704nw/+wpelkdig4FdwBoTkXIs=</DigestValue>
</Reference>
<Reference URI="lib%2Ftau%2Fwearable%2Ftheme%2Fbrown%2Fimages%2FPopup%2Ftw_toast_popup_image_bg.png">
<DigestMethod Algorithm="http://www.w3.org/2001/04/xmlenc#sha256"></DigestMethod>
<DigestValue>3mjrv/wd1wI4zGsbemLKWEA3ARYZyZF/lx8XLE87aSQ=</DigestValue>
</Reference>
<Reference URI="lib%2Ftau%2Fwearable%2Ftheme%2Fbrown%2Fimages%2FPopup%2Ftw_toast_popup_outline.png">
<DigestMethod Algorithm="http://www.w3.org/2001/04/xmlenc#sha256"></DigestMethod>
<DigestValue>mmYqlg9ixS5F00DUDkRiD8LJARxEPw7FwZpsINr4mwU=</DigestValue>
</Reference>
<Reference URI="lib%2Ftau%2Fwearable%2Ftheme%2Fbrown%2Fimages%2FProcessing%2Fprocessingfull.png">
<DigestMethod Algorithm="http://www.w3.org/2001/04/xmlenc#sha256"></DigestMethod>
<DigestValue>inphL/shFiOknwr0eLnUc7CGLICqacQ36GidvhaEuJ4=</DigestValue>
</Reference>
<Reference URI="lib%2Ftau%2Fwearable%2Ftheme%2Fbrown%2Fimages%2FProcessing%2Fprocessingsmall.png">
<DigestMethod Algorithm="http://www.w3.org/2001/04/xmlenc#sha256"></DigestMethod>
<DigestValue>C+hHn6OO+njwAy8GimgFpo+Owigwarpd0+/LdckPdjE=</DigestValue>
</Reference>
<Reference URI="lib%2Ftau%2Fwearable%2Ftheme%2Fbrown%2Fimages%2FScroller%2Fbouncing_bottom_edge.png">
<DigestMethod Algorithm="http://www.w3.org/2001/04/xmlenc#sha256"></DigestMethod>
<DigestValue>EwF0JIrEoFCTVRThWK/aNHTfqUzl+oQ5xaoEVeCKakQ=</DigestValue>
</Reference>
<Reference URI="lib%2Ftau%2Fwearable%2Ftheme%2Fbrown%2Fimages%2FScroller%2Fbouncing_bottom_glow.png">
<DigestMethod Algorithm="http://www.w3.org/2001/04/xmlenc#sha256"></DigestMethod>
<DigestValue>LBBYbeRMyt+BmcaK6OFcYxXCHatfcBy3WZmMEyeD494=</DigestValue>
</Reference>
<Reference URI="lib%2Ftau%2Fwearable%2Ftheme%2Fbrown%2Fimages%2FScroller%2Fbouncing_circle_bottom_edge.png">
<DigestMethod Algorithm="http://www.w3.org/2001/04/xmlenc#sha256"></DigestMethod>
<DigestValue>4zpEk6E15paDUijxsmbabMs46TeXF4D7uOr8yXUBnl0=</DigestValue>
</Reference>
<Reference URI="lib%2Ftau%2Fwearable%2Ftheme%2Fbrown%2Fimages%2FScroller%2Fbouncing_circle_bottom_glow.png">
<DigestMethod Algorithm="http://www.w3.org/2001/04/xmlenc#sha256"></DigestMethod>
<DigestValue>bcGdiIMylFL9ajYUoxh9Z+C/N1yfHdFvrvU4ocYLnoo=</DigestValue>
</Reference>
<Reference URI="lib%2Ftau%2Fwearable%2Ftheme%2Fbrown%2Fimages%2FScroller%2Fbouncing_circle_left_edge.png">
<DigestMethod Algorithm="http://www.w3.org/2001/04/xmlenc#sha256"></DigestMethod>
<DigestValue>IcYY9gteu+cywMJ4ccIK+y8X7RNqxdxY5Xnb2rfW9zg=</DigestValue>
</Reference>
<Reference URI="lib%2Ftau%2Fwearable%2Ftheme%2Fbrown%2Fimages%2FScroller%2Fbouncing_circle_left_glow.png">
<DigestMethod Algorithm="http://www.w3.org/2001/04/xmlenc#sha256"></DigestMethod>
<DigestValue>QJpek9IkYgeOa/DEUu0i+FJYw1G7pud0DErfVy6PtWI=</DigestValue>
</Reference>
<Reference URI="lib%2Ftau%2Fwearable%2Ftheme%2Fbrown%2Fimages%2FScroller%2Fbouncing_circle_right_edge.png">
<DigestMethod Algorithm="http://www.w3.org/2001/04/xmlenc#sha256"></DigestMethod>
<DigestValue>UoL95mMLn9oWwZKXx4xfcKQUd5BZICIiNovQ0X59zpU=</DigestValue>
</Reference>
<Reference URI="lib%2Ftau%2Fwearable%2Ftheme%2Fbrown%2Fimages%2FScroller%2Fbouncing_circle_right_glow.png">
<DigestMethod Algorithm="http://www.w3.org/2001/04/xmlenc#sha256"></DigestMethod>
<DigestValue>5KK+V+kpu/oD6Vd+6gE6JnOnJ29+ZI0ekabrdIX9dXs=</DigestValue>
</Reference>
<Reference URI="lib%2Ftau%2Fwearable%2Ftheme%2Fbrown%2Fimages%2FScroller%2Fbouncing_left_edge.png">
<DigestMethod Algorithm="http://www.w3.org/2001/04/xmlenc#sha256"></DigestMethod>
<DigestValue>ezbad2I+Qvqq+HBtFj5fCR73B7u1OpaGp8LbvJiksx8=</DigestValue>
</Reference>
<Reference URI="lib%2Ftau%2Fwearable%2Ftheme%2Fbrown%2Fimages%2FScroller%2Fbouncing_left_glow.png">
<DigestMethod Algorithm="http://www.w3.org/2001/04/xmlenc#sha256"></DigestMethod>
<DigestValue>i6payEnlv8vWHucju//UBssYNzmr3SES3nSuWDuJU6c=</DigestValue>
</Reference>
<Reference URI="lib%2Ftau%2Fwearable%2Ftheme%2Fbrown%2Fimages%2FScroller%2Fbouncing_right_edge.png">
<DigestMethod Algorithm="http://www.w3.org/2001/04/xmlenc#sha256"></DigestMethod>
<DigestValue>wIF0gTMZq7piBZ9E/+l5UgyW9pSywlBedaETJbK5euE=</DigestValue>
</Reference>
<Reference URI="lib%2Ftau%2Fwearable%2Ftheme%2Fbrown%2Fimages%2FScroller%2Fbouncing_right_glow.png">
<DigestMethod Algorithm="http://www.w3.org/2001/04/xmlenc#sha256"></DigestMethod>
<DigestValue>MZ/WXjPf0eoYefs4grYwm+dI4ehPs1D8ElGWv+wLcGk=</DigestValue>
</Reference>
<Reference URI="lib%2Ftau%2Fwearable%2Ftheme%2Fbrown%2Fimages%2FScroller%2Fbouncing_top_edge.png">
<DigestMethod Algorithm="http://www.w3.org/2001/04/xmlenc#sha256"></DigestMethod>
<DigestValue>iEpyiqHYkrP3GQpul3S6C87yG+PyVBWzhrmvxzPf//0=</DigestValue>
</Reference>
<Reference URI="lib%2Ftau%2Fwearable%2Ftheme%2Fbrown%2Fimages%2FScroller%2Fbouncing_top_glow.png">
<DigestMethod Algorithm="http://www.w3.org/2001/04/xmlenc#sha256"></DigestMethod>
<DigestValue>JmKqm+7nSe0dUkYRduPMoyyfc+Rg9gTVg2J7/pJq5F4=</DigestValue>
</Reference>
<Reference URI="lib%2Ftau%2Fwearable%2Ftheme%2Fbrown%2Fimages%2FSwipelist%2Fb_logs_icon_actionbar_btn_msg_nor.png">
<DigestMethod Algorithm="http://www.w3.org/2001/04/xmlenc#sha256"></DigestMethod>
<DigestValue>f6LUaSBsZsugcSX2A3xcaHs+rghK2nFAneqNp7WbOMw=</DigestValue>
</Reference>
<Reference URI="lib%2Ftau%2Fwearable%2Ftheme%2Fbrown%2Fimages%2FSwipelist%2Fb_logs_icon_body_btn_call_nor.png">
<DigestMethod Algorithm="http://www.w3.org/2001/04/xmlenc#sha256"></DigestMethod>
<DigestValue>fl7TG+5Mgf/y6KR8TdSEPcC/teaTrmRLm+lr9TSpOyg=</DigestValue>
</Reference>
<Reference URI="lib%2Ftau%2Fwearable%2Ftheme%2Fbrown%2Fimages%2FTitle_bar%2Fb_detail_bg_cover.png">
<DigestMethod Algorithm="http://www.w3.org/2001/04/xmlenc#sha256"></DigestMethod>
<DigestValue>6MewTgCyy7oMiEvq3KkLoNcPwf7TXOAoEtF14XSlYoM=</DigestValue>
</Reference>
<Reference URI="lib%2Ftau%2Fwearable%2Ftheme%2Fbrown%2Fimages%2Flistview%2Fb_list_focus_bg.png">
<DigestMethod Algorithm="http://www.w3.org/2001/04/xmlenc#sha256"></DigestMethod>
<DigestValue>Y2mvH98ij+UZgnL50uB1C7O0z7vycVJTo91w7YXqNL8=</DigestValue>
</Reference>
<Reference URI="lib%2Ftau%2Fwearable%2Ftheme%2Fbrown%2Fimages%2Flistview%2Fb_list_focus_bg_ef.png">
<DigestMethod Algorithm="http://www.w3.org/2001/04/xmlenc#sha256"></DigestMethod>
<DigestValue>esp0LccF3OAwLTU/MP0HKKyDwKxOSL+W+r5CkeMRlFs=</DigestValue>
</Reference>
<Reference URI="lib%2Ftau%2Fwearable%2Ftheme%2Fbrown%2Fimages%2Flistview%2Ftw_list_sub_line_left.png">
<DigestMethod Algorithm="http://www.w3.org/2001/04/xmlenc#sha256"></DigestMethod>
<DigestValue>shV08ijW9zUS7nWDPJJhii7sJ+I8PGnaiWIqM2eQupI=</DigestValue>
</Reference>
<Reference URI="lib%2Ftau%2Fwearable%2Ftheme%2Fbrown%2Fimages%2Flistview%2Ftw_list_sub_line_right.png">
<DigestMethod Algorithm="http://www.w3.org/2001/04/xmlenc#sha256"></DigestMethod>
<DigestValue>5bj8yP8hzh1GCTNeAEUIiVshD964KCede5tOIlybtZY=</DigestValue>
</Reference>
<Reference URI="lib%2Ftau%2Fwearable%2Ftheme%2Fbrown%2Ftau.css">
<DigestMethod Algorithm="http://www.w3.org/2001/04/xmlenc#sha256"></DigestMethod>
<DigestValue>TrclKhLRk0sQq+TU55IUF+9hg8UIgQ36CwNpdl6NscA=</DigestValue>
</Reference>
<Reference URI="lib%2Ftau%2Fwearable%2Ftheme%2Fbrown%2Ftau.min.css">
<DigestMethod Algorithm="http://www.w3.org/2001/04/xmlenc#sha256"></DigestMethod>
<DigestValue>5VZRu9UUTTOohXhXzxKvRNosTohqxCRcH4B8EVLVI90=</DigestValue>
</Reference>
<Reference URI="lib%2Ftau%2Fwearable%2Ftheme%2Fchangeable%2Fimages%2FActionbar%2Fb_more_option.png">
<DigestMethod Algorithm="http://www.w3.org/2001/04/xmlenc#sha256"></DigestMethod>
<DigestValue>kc1wJhzruwjgLS1vfPkmSQHz67R48K6bh8LpwjDuE+M=</DigestValue>
</Reference>
<Reference URI="lib%2Ftau%2Fwearable%2Ftheme%2Fchangeable%2Fimages%2FActionbar%2Ftw_ic_menu_moreoverflow_holo_dark.png">
<DigestMethod Algorithm="http://www.w3.org/2001/04/xmlenc#sha256"></DigestMethod>
<DigestValue>qkbuZm3KXZNobT9lxfhl6LdiG8ERnIdYMArm45mDI3g=</DigestValue>
</Reference>
<Reference URI="lib%2Ftau%2Fwearable%2Ftheme%2Fchangeable%2Fimages%2FCommon%2Fb_rotary_selector_center_pointer.png">
<DigestMethod Algorithm="http://www.w3.org/2001/04/xmlenc#sha256"></DigestMethod>
<DigestValue>jCnR9UxCYfKDwEXOuyk64OPrdV6jMH2gnTv7xxpT8pI=</DigestValue>
</Reference>
<Reference URI="lib%2Ftau%2Fwearable%2Ftheme%2Fchangeable%2Fimages%2FCommon%2Fmasking_bg.png">
<DigestMethod Algorithm="http://www.w3.org/2001/04/xmlenc#sha256"></DigestMethod>
<DigestValue>xg0blL/qm/PlWrv4gh9D5VbFduHT4mEgGpNRugTHpbo=</DigestValue>
</Reference>
<Reference URI="lib%2Ftau%2Fwearable%2Ftheme%2Fchangeable%2Fimages%2FController_icon%2FCheck%2Fref_btn_check_holo_dark.png">
<DigestMethod Algorithm="http://www.w3.org/2001/04/xmlenc#sha256"></DigestMethod>
<DigestValue>NWtT1Dj4doBFgGMhL/7RjdD1FG12IcjqwujPGK1PAmY=</DigestValue>
</Reference>
<Reference URI="lib%2Ftau%2Fwearable%2Ftheme%2Fchangeable%2Fimages%2FController_icon%2FCheck%2Ftw_btn_check_bg_holo_dark.png">
<DigestMethod Algorithm="http://www.w3.org/2001/04/xmlenc#sha256"></DigestMethod>
<DigestValue>ukc3arzEQ6qP3AHgftAkBtwZyuc0q3JNL2lro88eYak=</DigestValue>
</Reference>
<Reference URI="lib%2Ftau%2Fwearable%2Ftheme%2Fchangeable%2Fimages%2FController_icon%2FCheck%2Ftw_btn_check_holo_dark.png">
<DigestMethod Algorithm="http://www.w3.org/2001/04/xmlenc#sha256"></DigestMethod>
<DigestValue>t2riLxtAI1RWhbl6os4UkxBGczwhJFdUFF7DNcka9zM=</DigestValue>
</Reference>
<Reference URI="lib%2Ftau%2Fwearable%2Ftheme%2Fchangeable%2Fimages%2FController_icon%2FOn_Off%2Ftw_btn_control_bg_holo_dark.png">
<DigestMethod Algorithm="http://www.w3.org/2001/04/xmlenc#sha256"></DigestMethod>
<DigestValue>GbaaRiAZjvqf/AcpgD940qqHEcseOMFWnu8ham//jTg=</DigestValue>
</Reference>
<Reference URI="lib%2Ftau%2Fwearable%2Ftheme%2Fchangeable%2Fimages%2FController_icon%2FOn_Off%2Ftw_btn_control_off_holo_dark.png">
<DigestMethod Algorithm="http://www.w3.org/2001/04/xmlenc#sha256"></DigestMethod>
<DigestValue>N06Ed3Ihxxo2MldtVQKRq0qYl1eRbuo0zEe2medE1J0=</DigestValue>
</Reference>
<Reference URI="lib%2Ftau%2Fwearable%2Ftheme%2Fchangeable%2Fimages%2FController_icon%2FOn_Off%2Ftw_btn_control_on_holo_dark.png">
<DigestMethod Algorithm="http://www.w3.org/2001/04/xmlenc#sha256"></DigestMethod>
<DigestValue>ph0ljcHGNXlJO1dPAiAQgDpRH3+mbMZZ3Ega7lNW/cw=</DigestValue>
</Reference>
<Reference URI="lib%2Ftau%2Fwearable%2Ftheme%2Fchangeable%2Fimages%2FController_icon%2FRadio%2Ftw_btn_radio_holo_dark.png">
<DigestMethod Algorithm="http://www.w3.org/2001/04/xmlenc#sha256"></DigestMethod>
<DigestValue>3i13zlE5UUPepY9sbRmsu3oxYmIBCpM9hwL0YyiVaEI=</DigestValue>
</Reference>
<Reference URI="lib%2Ftau%2Fwearable%2Ftheme%2Fchangeable%2Fimages%2FController_icon%2Ftoggle_changeable.png">
<DigestMethod Algorithm="http://www.w3.org/2001/04/xmlenc#sha256"></DigestMethod>
<DigestValue>BzK0UNVeSZCohwIBfIkqCru85HE/86q/2MZUEQJWcoU=</DigestValue>
</Reference>
<Reference URI="lib%2Ftau%2Fwearable%2Ftheme%2Fchangeable%2Fimages%2FController_icon%2Ftw_btn_check_holo_dark.png">
<DigestMethod Algorithm="http://www.w3.org/2001/04/xmlenc#sha256"></DigestMethod>
<DigestValue>qFC8fOl6Tg7LrLrT62RSQLKSr3GP6O2UwjnG9s7DAck=</DigestValue>
</Reference>
<Reference URI="lib%2Ftau%2Fwearable%2Ftheme%2Fchangeable%2Fimages%2FController_icon%2Ftw_btn_checkbox_holo_dark.png">
<DigestMethod Algorithm="http://www.w3.org/2001/04/xmlenc#sha256"></DigestMethod>
<DigestValue>ddihq2E6gV6+g48CtlRBvDFnKx97KWUJxoNr8SQ7sUQ=</DigestValue>
</Reference>
<Reference URI="lib%2Ftau%2Fwearable%2Ftheme%2Fchangeable%2Fimages%2FController_icon%2Ftw_btn_checkbox_line_holo_dark.png">
<DigestMethod Algorithm="http://www.w3.org/2001/04/xmlenc#sha256"></DigestMethod>
<DigestValue>elPeRLEot+b5h79G5sudnUNkc6GhAyye82uL2cn9xxc=</DigestValue>
</Reference>
<Reference URI="lib%2Ftau%2Fwearable%2Ftheme%2Fchangeable%2Fimages%2FController_icon%2Ftw_btn_radio_holo_dark.png">
<DigestMethod Algorithm="http://www.w3.org/2001/04/xmlenc#sha256"></DigestMethod>
<DigestValue>SYKDGM5OUHfYf65YinTD2vzNNMNUjKEABJaxy/68hv4=</DigestValue>
</Reference>
<Reference URI="lib%2Ftau%2Fwearable%2Ftheme%2Fchangeable%2Fimages%2FController_icon%2Ftw_btn_radiobox_holo_dark.png">
<DigestMethod Algorithm="http://www.w3.org/2001/04/xmlenc#sha256"></DigestMethod>
<DigestValue>nwK+t+eTDiAjgXRMhNpbO52ccNtX1T8to7iUEfvtEw0=</DigestValue>
</Reference>
<Reference URI="lib%2Ftau%2Fwearable%2Ftheme%2Fchangeable%2Fimages%2FController_icon%2Ftw_btn_radiobox_line.png">
<DigestMethod Algorithm="http://www.w3.org/2001/04/xmlenc#sha256"></DigestMethod>
<DigestValue>JXfJFsytb7Ca9bHn2mZ7J5UVde6gr5WIQWFARUEbSAI=</DigestValue>
</Reference>
<Reference URI="lib%2Ftau%2Fwearable%2Ftheme%2Fchangeable%2Fimages%2FIndicator%2Fb_fast_scroll_rollover_bg.png">
<DigestMethod Algorithm="http://www.w3.org/2001/04/xmlenc#sha256"></DigestMethod>
<DigestValue>BdM1nG2OXAGZ/Jjerne40hr4z+CUVQDaGGDC9NKHbJ4=</DigestValue>
</Reference>
<Reference URI="lib%2Ftau%2Fwearable%2Ftheme%2Fchangeable%2Fimages%2FIndicator%2Fb_index_scroll_bg.png">
<DigestMethod Algorithm="http://www.w3.org/2001/04/xmlenc#sha256"></DigestMethod>
<DigestValue>G1lZylmCqAW+9pxtAqkRcvWmAaqrhmKmFNQ6S+Gfofo=</DigestValue>
</Reference>
<Reference URI="lib%2Ftau%2Fwearable%2Ftheme%2Fchangeable%2Fimages%2FIndicator%2Flist_scroll_triggle.png">
<DigestMethod Algorithm="http://www.w3.org/2001/04/xmlenc#sha256"></DigestMethod>
<DigestValue>7GQe3ejeCKtt6U+41MqwJ8q3SaU7cwmfF1sFnFygjCw=</DigestValue>
</Reference>
<Reference URI="lib%2Ftau%2Fwearable%2Ftheme%2Fchangeable%2Fimages%2FList%2Fb_body_edge_shadow.png">
<DigestMethod Algorithm="http://www.w3.org/2001/04/xmlenc#sha256"></DigestMethod>
<DigestValue>xUE9SahpNHNokTSvhfV04BMB0Mdz4wsHy22HYi+93B4=</DigestValue>
</Reference>
<Reference URI="lib%2Ftau%2Fwearable%2Ftheme%2Fchangeable%2Fimages%2FList%2Fb_list_focus_bg_108.png">
<DigestMethod Algorithm="http://www.w3.org/2001/04/xmlenc#sha256"></DigestMethod>
<DigestValue>Ds+e1ERJ7fKikfUF7LTSOFWaGS08JNA/R1xFTPfyGxY=</DigestValue>
</Reference>
<Reference URI="lib%2Ftau%2Fwearable%2Ftheme%2Fchangeable%2Fimages%2FPopup%2Fb_popup_edge_inner_glow.png">
<DigestMethod Algorithm="http://www.w3.org/2001/04/xmlenc#sha256"></DigestMethod>
<DigestValue>SAnFR0QqrmaF1Sq9WO6N22n4KCuOr0yiCxSelMuIlIo=</DigestValue>
</Reference>
<Reference URI="lib%2Ftau%2Fwearable%2Ftheme%2Fchangeable%2Fimages%2FPopup%2Fb_popup_edge_shadow.png">
<DigestMethod Algorithm="http://www.w3.org/2001/04/xmlenc#sha256"></DigestMethod>
<DigestValue>spXDbatBHTzSFR4N03w93hLrVybuw/XRjZAfneskshI=</DigestValue>
</Reference>
<Reference URI="lib%2Ftau%2Fwearable%2Ftheme%2Fchangeable%2Fimages%2FPopup%2Ftoast_check.png">
<DigestMethod Algorithm="http://www.w3.org/2001/04/xmlenc#sha256"></DigestMethod>
<DigestValue>l7tDb2GpWcNj93JU9VgQbbDgqEtDA7bdufKK12uMkPs=</DigestValue>
</Reference>
<Reference URI="lib%2Ftau%2Fwearable%2Ftheme%2Fchangeable%2Fimages%2FPopup%2Ftw_popup_bg.png">
<DigestMethod Algorithm="http://www.w3.org/2001/04/xmlenc#sha256"></DigestMethod>
<DigestValue>TphpTsohWyWK9j+2DXpOyvJSydRMq2Av5B0otjA9f9I=</DigestValue>
</Reference>
<Reference URI="lib%2Ftau%2Fwearable%2Ftheme%2Fchangeable%2Fimages%2FPopup%2Ftw_popup_bg_cover.png">
<DigestMethod Algorithm="http://www.w3.org/2001/04/xmlenc#sha256"></DigestMethod>
<DigestValue>vqXi7pK9urSnMFrdVlcc8IFvLcUduAMNIIgbnFvQc4A=</DigestValue>
</Reference>
<Reference URI="lib%2Ftau%2Fwearable%2Ftheme%2Fchangeable%2Fimages%2FPopup%2Ftw_toast_popup_bg.png">
<DigestMethod Algorithm="http://www.w3.org/2001/04/xmlenc#sha256"></DigestMethod>
<DigestValue>HQr3u9+djLy7CqBURR3qMnfvWxQRk+7KsyluA9KadzQ=</DigestValue>
</Reference>
<Reference URI="lib%2Ftau%2Fwearable%2Ftheme%2Fchangeable%2Fimages%2FPopup%2Ftw_toast_popup_bg_cover.png">
<DigestMethod Algorithm="http://www.w3.org/2001/04/xmlenc#sha256"></DigestMethod>
<DigestValue>PTz1Q9tb2jmV/h/NF704nw/+wpelkdig4FdwBoTkXIs=</DigestValue>
</Reference>
<Reference URI="lib%2Ftau%2Fwearable%2Ftheme%2Fchangeable%2Fimages%2FPopup%2Ftw_toast_popup_image_bg.png">
<DigestMethod Algorithm="http://www.w3.org/2001/04/xmlenc#sha256"></DigestMethod>
<DigestValue>3mjrv/wd1wI4zGsbemLKWEA3ARYZyZF/lx8XLE87aSQ=</DigestValue>
</Reference>
<Reference URI="lib%2Ftau%2Fwearable%2Ftheme%2Fchangeable%2Fimages%2FPopup%2Ftw_toast_popup_outline.png">
<DigestMethod Algorithm="http://www.w3.org/2001/04/xmlenc#sha256"></DigestMethod>
<DigestValue>mmYqlg9ixS5F00DUDkRiD8LJARxEPw7FwZpsINr4mwU=</DigestValue>
</Reference>
<Reference URI="lib%2Ftau%2Fwearable%2Ftheme%2Fchangeable%2Fimages%2FProcessing%2Fprocessingfull.png">
<DigestMethod Algorithm="http://www.w3.org/2001/04/xmlenc#sha256"></DigestMethod>
<DigestValue>inphL/shFiOknwr0eLnUc7CGLICqacQ36GidvhaEuJ4=</DigestValue>
</Reference>
<Reference URI="lib%2Ftau%2Fwearable%2Ftheme%2Fchangeable%2Fimages%2FProcessing%2Fprocessingsmall.png">
<DigestMethod Algorithm="http://www.w3.org/2001/04/xmlenc#sha256"></DigestMethod>
<DigestValue>C+hHn6OO+njwAy8GimgFpo+Owigwarpd0+/LdckPdjE=</DigestValue>
</Reference>
<Reference URI="lib%2Ftau%2Fwearable%2Ftheme%2Fchangeable%2Fimages%2FScroller%2Fbouncing_bottom_edge.png">
<DigestMethod Algorithm="http://www.w3.org/2001/04/xmlenc#sha256"></DigestMethod>
<DigestValue>EwF0JIrEoFCTVRThWK/aNHTfqUzl+oQ5xaoEVeCKakQ=</DigestValue>
</Reference>
<Reference URI="lib%2Ftau%2Fwearable%2Ftheme%2Fchangeable%2Fimages%2FScroller%2Fbouncing_bottom_glow.png">
<DigestMethod Algorithm="http://www.w3.org/2001/04/xmlenc#sha256"></DigestMethod>
<DigestValue>LBBYbeRMyt+BmcaK6OFcYxXCHatfcBy3WZmMEyeD494=</DigestValue>
</Reference>
<Reference URI="lib%2Ftau%2Fwearable%2Ftheme%2Fchangeable%2Fimages%2FScroller%2Fbouncing_circle_bottom_edge.png">
<DigestMethod Algorithm="http://www.w3.org/2001/04/xmlenc#sha256"></DigestMethod>
<DigestValue>4zpEk6E15paDUijxsmbabMs46TeXF4D7uOr8yXUBnl0=</DigestValue>
</Reference>
<Reference URI="lib%2Ftau%2Fwearable%2Ftheme%2Fchangeable%2Fimages%2FScroller%2Fbouncing_circle_bottom_glow.png">
<DigestMethod Algorithm="http://www.w3.org/2001/04/xmlenc#sha256"></DigestMethod>
<DigestValue>bcGdiIMylFL9ajYUoxh9Z+C/N1yfHdFvrvU4ocYLnoo=</DigestValue>
</Reference>
<Reference URI="lib%2Ftau%2Fwearable%2Ftheme%2Fchangeable%2Fimages%2FScroller%2Fbouncing_circle_left_edge.png">
<DigestMethod Algorithm="http://www.w3.org/2001/04/xmlenc#sha256"></DigestMethod>
<DigestValue>IcYY9gteu+cywMJ4ccIK+y8X7RNqxdxY5Xnb2rfW9zg=</DigestValue>
</Reference>
<Reference URI="lib%2Ftau%2Fwearable%2Ftheme%2Fchangeable%2Fimages%2FScroller%2Fbouncing_circle_left_glow.png">
<DigestMethod Algorithm="http://www.w3.org/2001/04/xmlenc#sha256"></DigestMethod>
<DigestValue>QJpek9IkYgeOa/DEUu0i+FJYw1G7pud0DErfVy6PtWI=</DigestValue>
</Reference>
<Reference URI="lib%2Ftau%2Fwearable%2Ftheme%2Fchangeable%2Fimages%2FScroller%2Fbouncing_circle_right_edge.png">
<DigestMethod Algorithm="http://www.w3.org/2001/04/xmlenc#sha256"></DigestMethod>
<DigestValue>UoL95mMLn9oWwZKXx4xfcKQUd5BZICIiNovQ0X59zpU=</DigestValue>
</Reference>
<Reference URI="lib%2Ftau%2Fwearable%2Ftheme%2Fchangeable%2Fimages%2FScroller%2Fbouncing_circle_right_glow.png">
<DigestMethod Algorithm="http://www.w3.org/2001/04/xmlenc#sha256"></DigestMethod>
<DigestValue>5KK+V+kpu/oD6Vd+6gE6JnOnJ29+ZI0ekabrdIX9dXs=</DigestValue>
</Reference>
<Reference URI="lib%2Ftau%2Fwearable%2Ftheme%2Fchangeable%2Fimages%2FScroller%2Fbouncing_left_edge.png">
<DigestMethod Algorithm="http://www.w3.org/2001/04/xmlenc#sha256"></DigestMethod>
<DigestValue>ezbad2I+Qvqq+HBtFj5fCR73B7u1OpaGp8LbvJiksx8=</DigestValue>
</Reference>
<Reference URI="lib%2Ftau%2Fwearable%2Ftheme%2Fchangeable%2Fimages%2FScroller%2Fbouncing_left_glow.png">
<DigestMethod Algorithm="http://www.w3.org/2001/04/xmlenc#sha256"></DigestMethod>
<DigestValue>i6payEnlv8vWHucju//UBssYNzmr3SES3nSuWDuJU6c=</DigestValue>
</Reference>
<Reference URI="lib%2Ftau%2Fwearable%2Ftheme%2Fchangeable%2Fimages%2FScroller%2Fbouncing_right_edge.png">
<DigestMethod Algorithm="http://www.w3.org/2001/04/xmlenc#sha256"></DigestMethod>
<DigestValue>wIF0gTMZq7piBZ9E/+l5UgyW9pSywlBedaETJbK5euE=</DigestValue>
</Reference>
<Reference URI="lib%2Ftau%2Fwearable%2Ftheme%2Fchangeable%2Fimages%2FScroller%2Fbouncing_right_glow.png">
<DigestMethod Algorithm="http://www.w3.org/2001/04/xmlenc#sha256"></DigestMethod>
<DigestValue>MZ/WXjPf0eoYefs4grYwm+dI4ehPs1D8ElGWv+wLcGk=</DigestValue>
</Reference>
<Reference URI="lib%2Ftau%2Fwearable%2Ftheme%2Fchangeable%2Fimages%2FScroller%2Fbouncing_top_edge.png">
<DigestMethod Algorithm="http://www.w3.org/2001/04/xmlenc#sha256"></DigestMethod>
<DigestValue>iEpyiqHYkrP3GQpul3S6C87yG+PyVBWzhrmvxzPf//0=</DigestValue>
</Reference>
<Reference URI="lib%2Ftau%2Fwearable%2Ftheme%2Fchangeable%2Fimages%2FScroller%2Fbouncing_top_glow.png">
<DigestMethod Algorithm="http://www.w3.org/2001/04/xmlenc#sha256"></DigestMethod>
<DigestValue>JmKqm+7nSe0dUkYRduPMoyyfc+Rg9gTVg2J7/pJq5F4=</DigestValue>
</Reference>
<Reference URI="lib%2Ftau%2Fwearable%2Ftheme%2Fchangeable%2Fimages%2FSwipelist%2Fb_logs_icon_actionbar_btn_msg_nor.png">
<DigestMethod Algorithm="http://www.w3.org/2001/04/xmlenc#sha256"></DigestMethod>
<DigestValue>f6LUaSBsZsugcSX2A3xcaHs+rghK2nFAneqNp7WbOMw=</DigestValue>
</Reference>
<Reference URI="lib%2Ftau%2Fwearable%2Ftheme%2Fchangeable%2Fimages%2FSwipelist%2Fb_logs_icon_body_btn_call_nor.png">
<DigestMethod Algorithm="http://www.w3.org/2001/04/xmlenc#sha256"></DigestMethod>
<DigestValue>fl7TG+5Mgf/y6KR8TdSEPcC/teaTrmRLm+lr9TSpOyg=</DigestValue>
</Reference>
<Reference URI="lib%2Ftau%2Fwearable%2Ftheme%2Fchangeable%2Fimages%2FTitle_bar%2Fb_detail_bg_cover.png">
<DigestMethod Algorithm="http://www.w3.org/2001/04/xmlenc#sha256"></DigestMethod>
<DigestValue>6MewTgCyy7oMiEvq3KkLoNcPwf7TXOAoEtF14XSlYoM=</DigestValue>
</Reference>
<Reference URI="lib%2Ftau%2Fwearable%2Ftheme%2Fchangeable%2Fimages%2Flistview%2Fb_list_focus_bg.png">
<DigestMethod Algorithm="http://www.w3.org/2001/04/xmlenc#sha256"></DigestMethod>
<DigestValue>Y2mvH98ij+UZgnL50uB1C7O0z7vycVJTo91w7YXqNL8=</DigestValue>
</Reference>
<Reference URI="lib%2Ftau%2Fwearable%2Ftheme%2Fchangeable%2Fimages%2Flistview%2Fb_list_focus_bg_ef.png">
<DigestMethod Algorithm="http://www.w3.org/2001/04/xmlenc#sha256"></DigestMethod>
<DigestValue>esp0LccF3OAwLTU/MP0HKKyDwKxOSL+W+r5CkeMRlFs=</DigestValue>
</Reference>
<Reference URI="lib%2Ftau%2Fwearable%2Ftheme%2Fchangeable%2Fimages%2Flistview%2Ftw_list_sub_line_left.png">
<DigestMethod Algorithm="http://www.w3.org/2001/04/xmlenc#sha256"></DigestMethod>
<DigestValue>shV08ijW9zUS7nWDPJJhii7sJ+I8PGnaiWIqM2eQupI=</DigestValue>
</Reference>
<Reference URI="lib%2Ftau%2Fwearable%2Ftheme%2Fchangeable%2Fimages%2Flistview%2Ftw_list_sub_line_right.png">
<DigestMethod Algorithm="http://www.w3.org/2001/04/xmlenc#sha256"></DigestMethod>
<DigestValue>5bj8yP8hzh1GCTNeAEUIiVshD964KCede5tOIlybtZY=</DigestValue>
</Reference>
<Reference URI="lib%2Ftau%2Fwearable%2Ftheme%2Fchangeable%2Ftau.circle.css">
<DigestMethod Algorithm="http://www.w3.org/2001/04/xmlenc#sha256"></DigestMethod>
<DigestValue>frManZad6BQ21GdIQdyuVFJleqSbYhhjeigrvJTYEWo=</DigestValue>
</Reference>
<Reference URI="lib%2Ftau%2Fwearable%2Ftheme%2Fchangeable%2Ftau.circle.min.css">
<DigestMethod Algorithm="http://www.w3.org/2001/04/xmlenc#sha256"></DigestMethod>
<DigestValue>/Tmdpl/VCn3Gl/FbOcPJXePOS5shjuVeA8FfClJeLbs=</DigestValue>
</Reference>
<Reference URI="lib%2Ftau%2Fwearable%2Ftheme%2Fchangeable%2Ftau.circle.min.template">
<DigestMethod Algorithm="http://www.w3.org/2001/04/xmlenc#sha256"></DigestMethod>
<DigestValue>JTiueoTgaMlzv+qwtryN5WtoTKpsmSTNt7F8Yyzsrwc=</DigestValue>
</Reference>
<Reference URI="lib%2Ftau%2Fwearable%2Ftheme%2Fchangeable%2Ftau.circle.template">
<DigestMethod Algorithm="http://www.w3.org/2001/04/xmlenc#sha256"></DigestMethod>
<DigestValue>27zwKy5PHa/D+71uQeYBcffitNUOXlUpJ3uKAV0CTEk=</DigestValue>
</Reference>
<Reference URI="lib%2Ftau%2Fwearable%2Ftheme%2Fchangeable%2Ftau.css">
<DigestMethod Algorithm="http://www.w3.org/2001/04/xmlenc#sha256"></DigestMethod>
<DigestValue>TtVuteUo5uSKfc8FyqVEv2u+KeqXKRtfJ1gkPXoyMgI=</DigestValue>
</Reference>
<Reference URI="lib%2Ftau%2Fwearable%2Ftheme%2Fchangeable%2Ftau.min.css">
<DigestMethod Algorithm="http://www.w3.org/2001/04/xmlenc#sha256"></DigestMethod>
<DigestValue>nlqraPG4D/iUagIpoBeMNu6hxtPooUhsWr4K83m4tPg=</DigestValue>
</Reference>
<Reference URI="lib%2Ftau%2Fwearable%2Ftheme%2Fchangeable%2Ftau.min.template">
<DigestMethod Algorithm="http://www.w3.org/2001/04/xmlenc#sha256"></DigestMethod>
<DigestValue>y4Owv6ufluDCgsH+THhfcqqVvkgxBY8oZshUX51+WxM=</DigestValue>
</Reference>
<Reference URI="lib%2Ftau%2Fwearable%2Ftheme%2Fchangeable%2Ftau.template">
<DigestMethod Algorithm="http://www.w3.org/2001/04/xmlenc#sha256"></DigestMethod>
<DigestValue>slIRwwX/GVB+piMwvHdlKEwqa/zzvk9oCvKm00QkC+U=</DigestValue>
</Reference>
<Reference URI="lib%2Ftau%2Fwearable%2Ftheme%2Fdefault%2Fimages%2FActionbar%2Fb_more_option.png">
<DigestMethod Algorithm="http://www.w3.org/2001/04/xmlenc#sha256"></DigestMethod>
<DigestValue>kc1wJhzruwjgLS1vfPkmSQHz67R48K6bh8LpwjDuE+M=</DigestValue>
</Reference>
<Reference URI="lib%2Ftau%2Fwearable%2Ftheme%2Fdefault%2Fimages%2FActionbar%2Ftw_ic_menu_moreoverflow_holo_dark.png">
<DigestMethod Algorithm="http://www.w3.org/2001/04/xmlenc#sha256"></DigestMethod>
<DigestValue>qkbuZm3KXZNobT9lxfhl6LdiG8ERnIdYMArm45mDI3g=</DigestValue>
</Reference>
<Reference URI="lib%2Ftau%2Fwearable%2Ftheme%2Fdefault%2Fimages%2FCommon%2Fb_rotary_selector_center_pointer.png">
<DigestMethod Algorithm="http://www.w3.org/2001/04/xmlenc#sha256"></DigestMethod>
<DigestValue>jCnR9UxCYfKDwEXOuyk64OPrdV6jMH2gnTv7xxpT8pI=</DigestValue>
</Reference>
<Reference URI="lib%2Ftau%2Fwearable%2Ftheme%2Fdefault%2Fimages%2FCommon%2Fmasking_bg.png">
<DigestMethod Algorithm="http://www.w3.org/2001/04/xmlenc#sha256"></DigestMethod>
<DigestValue>xg0blL/qm/PlWrv4gh9D5VbFduHT4mEgGpNRugTHpbo=</DigestValue>
</Reference>
<Reference URI="lib%2Ftau%2Fwearable%2Ftheme%2Fdefault%2Fimages%2FController_icon%2FCheck%2Fref_btn_check_holo_dark.png">
<DigestMethod Algorithm="http://www.w3.org/2001/04/xmlenc#sha256"></DigestMethod>
<DigestValue>NWtT1Dj4doBFgGMhL/7RjdD1FG12IcjqwujPGK1PAmY=</DigestValue>
</Reference>
<Reference URI="lib%2Ftau%2Fwearable%2Ftheme%2Fdefault%2Fimages%2FController_icon%2FCheck%2Ftw_btn_check_bg_holo_dark.png">
<DigestMethod Algorithm="http://www.w3.org/2001/04/xmlenc#sha256"></DigestMethod>
<DigestValue>ukc3arzEQ6qP3AHgftAkBtwZyuc0q3JNL2lro88eYak=</DigestValue>
</Reference>
<Reference URI="lib%2Ftau%2Fwearable%2Ftheme%2Fdefault%2Fimages%2FController_icon%2FCheck%2Ftw_btn_check_holo_dark.png">
<DigestMethod Algorithm="http://www.w3.org/2001/04/xmlenc#sha256"></DigestMethod>
<DigestValue>t2riLxtAI1RWhbl6os4UkxBGczwhJFdUFF7DNcka9zM=</DigestValue>
</Reference>
<Reference URI="lib%2Ftau%2Fwearable%2Ftheme%2Fdefault%2Fimages%2FController_icon%2FOn_Off%2Ftw_btn_control_bg_holo_dark.png">
<DigestMethod Algorithm="http://www.w3.org/2001/04/xmlenc#sha256"></DigestMethod>
<DigestValue>GbaaRiAZjvqf/AcpgD940qqHEcseOMFWnu8ham//jTg=</DigestValue>
</Reference>
<Reference URI="lib%2Ftau%2Fwearable%2Ftheme%2Fdefault%2Fimages%2FController_icon%2FOn_Off%2Ftw_btn_control_off_holo_dark.png">
<DigestMethod Algorithm="http://www.w3.org/2001/04/xmlenc#sha256"></DigestMethod>
<DigestValue>N06Ed3Ihxxo2MldtVQKRq0qYl1eRbuo0zEe2medE1J0=</DigestValue>
</Reference>
<Reference URI="lib%2Ftau%2Fwearable%2Ftheme%2Fdefault%2Fimages%2FController_icon%2FOn_Off%2Ftw_btn_control_on_holo_dark.png">
<DigestMethod Algorithm="http://www.w3.org/2001/04/xmlenc#sha256"></DigestMethod>
<DigestValue>ph0ljcHGNXlJO1dPAiAQgDpRH3+mbMZZ3Ega7lNW/cw=</DigestValue>
</Reference>
<Reference URI="lib%2Ftau%2Fwearable%2Ftheme%2Fdefault%2Fimages%2FController_icon%2FRadio%2Ftw_btn_radio_holo_dark.png">
<DigestMethod Algorithm="http://www.w3.org/2001/04/xmlenc#sha256"></DigestMethod>
<DigestValue>3i13zlE5UUPepY9sbRmsu3oxYmIBCpM9hwL0YyiVaEI=</DigestValue>
</Reference>
<Reference URI="lib%2Ftau%2Fwearable%2Ftheme%2Fdefault%2Fimages%2FController_icon%2Ftoggle_changeable.png">
<DigestMethod Algorithm="http://www.w3.org/2001/04/xmlenc#sha256"></DigestMethod>
<DigestValue>BzK0UNVeSZCohwIBfIkqCru85HE/86q/2MZUEQJWcoU=</DigestValue>
</Reference>
<Reference URI="lib%2Ftau%2Fwearable%2Ftheme%2Fdefault%2Fimages%2FController_icon%2Ftw_btn_check_holo_dark.png">
<DigestMethod Algorithm="http://www.w3.org/2001/04/xmlenc#sha256"></DigestMethod>
<DigestValue>qFC8fOl6Tg7LrLrT62RSQLKSr3GP6O2UwjnG9s7DAck=</DigestValue>
</Reference>
<Reference URI="lib%2Ftau%2Fwearable%2Ftheme%2Fdefault%2Fimages%2FController_icon%2Ftw_btn_checkbox_holo_dark.png">
<DigestMethod Algorithm="http://www.w3.org/2001/04/xmlenc#sha256"></DigestMethod>
<DigestValue>ddihq2E6gV6+g48CtlRBvDFnKx97KWUJxoNr8SQ7sUQ=</DigestValue>
</Reference>
<Reference URI="lib%2Ftau%2Fwearable%2Ftheme%2Fdefault%2Fimages%2FController_icon%2Ftw_btn_checkbox_line_holo_dark.png">
<DigestMethod Algorithm="http://www.w3.org/2001/04/xmlenc#sha256"></DigestMethod>
<DigestValue>elPeRLEot+b5h79G5sudnUNkc6GhAyye82uL2cn9xxc=</DigestValue>
</Reference>
<Reference URI="lib%2Ftau%2Fwearable%2Ftheme%2Fdefault%2Fimages%2FController_icon%2Ftw_btn_radio_holo_dark.png">
<DigestMethod Algorithm="http://www.w3.org/2001/04/xmlenc#sha256"></DigestMethod>
<DigestValue>SYKDGM5OUHfYf65YinTD2vzNNMNUjKEABJaxy/68hv4=</DigestValue>
</Reference>
<Reference URI="lib%2Ftau%2Fwearable%2Ftheme%2Fdefault%2Fimages%2FController_icon%2Ftw_btn_radiobox_holo_dark.png">
<DigestMethod Algorithm="http://www.w3.org/2001/04/xmlenc#sha256"></DigestMethod>
<DigestValue>nwK+t+eTDiAjgXRMhNpbO52ccNtX1T8to7iUEfvtEw0=</DigestValue>
</Reference>
<Reference URI="lib%2Ftau%2Fwearable%2Ftheme%2Fdefault%2Fimages%2FController_icon%2Ftw_btn_radiobox_line.png">
<DigestMethod Algorithm="http://www.w3.org/2001/04/xmlenc#sha256"></DigestMethod>
<DigestValue>JXfJFsytb7Ca9bHn2mZ7J5UVde6gr5WIQWFARUEbSAI=</DigestValue>
</Reference>
<Reference URI="lib%2Ftau%2Fwearable%2Ftheme%2Fdefault%2Fimages%2FIndicator%2Fb_fast_scroll_rollover_bg.png">
<DigestMethod Algorithm="http://www.w3.org/2001/04/xmlenc#sha256"></DigestMethod>
<DigestValue>BdM1nG2OXAGZ/Jjerne40hr4z+CUVQDaGGDC9NKHbJ4=</DigestValue>
</Reference>
<Reference URI="lib%2Ftau%2Fwearable%2Ftheme%2Fdefault%2Fimages%2FIndicator%2Fb_index_scroll_bg.png">
<DigestMethod Algorithm="http://www.w3.org/2001/04/xmlenc#sha256"></DigestMethod>
<DigestValue>G1lZylmCqAW+9pxtAqkRcvWmAaqrhmKmFNQ6S+Gfofo=</DigestValue>
</Reference>
<Reference URI="lib%2Ftau%2Fwearable%2Ftheme%2Fdefault%2Fimages%2FIndicator%2Flist_scroll_triggle.png">
<DigestMethod Algorithm="http://www.w3.org/2001/04/xmlenc#sha256"></DigestMethod>
<DigestValue>7GQe3ejeCKtt6U+41MqwJ8q3SaU7cwmfF1sFnFygjCw=</DigestValue>
</Reference>
<Reference URI="lib%2Ftau%2Fwearable%2Ftheme%2Fdefault%2Fimages%2FList%2Fb_body_edge_shadow.png">
<DigestMethod Algorithm="http://www.w3.org/2001/04/xmlenc#sha256"></DigestMethod>
<DigestValue>xUE9SahpNHNokTSvhfV04BMB0Mdz4wsHy22HYi+93B4=</DigestValue>
</Reference>
<Reference URI="lib%2Ftau%2Fwearable%2Ftheme%2Fdefault%2Fimages%2FList%2Fb_list_focus_bg_108.png">
<DigestMethod Algorithm="http://www.w3.org/2001/04/xmlenc#sha256"></DigestMethod>
<DigestValue>Ds+e1ERJ7fKikfUF7LTSOFWaGS08JNA/R1xFTPfyGxY=</DigestValue>
</Reference>
<Reference URI="lib%2Ftau%2Fwearable%2Ftheme%2Fdefault%2Fimages%2FPopup%2Fb_popup_edge_inner_glow.png">
<DigestMethod Algorithm="http://www.w3.org/2001/04/xmlenc#sha256"></DigestMethod>
<DigestValue>SAnFR0QqrmaF1Sq9WO6N22n4KCuOr0yiCxSelMuIlIo=</DigestValue>
</Reference>
<Reference URI="lib%2Ftau%2Fwearable%2Ftheme%2Fdefault%2Fimages%2FPopup%2Fb_popup_edge_shadow.png">
<DigestMethod Algorithm="http://www.w3.org/2001/04/xmlenc#sha256"></DigestMethod>
<DigestValue>spXDbatBHTzSFR4N03w93hLrVybuw/XRjZAfneskshI=</DigestValue>
</Reference>
<Reference URI="lib%2Ftau%2Fwearable%2Ftheme%2Fdefault%2Fimages%2FPopup%2Ftoast_check.png">
<DigestMethod Algorithm="http://www.w3.org/2001/04/xmlenc#sha256"></DigestMethod>
<DigestValue>l7tDb2GpWcNj93JU9VgQbbDgqEtDA7bdufKK12uMkPs=</DigestValue>
</Reference>
<Reference URI="lib%2Ftau%2Fwearable%2Ftheme%2Fdefault%2Fimages%2FPopup%2Ftw_popup_bg.png">
<DigestMethod Algorithm="http://www.w3.org/2001/04/xmlenc#sha256"></DigestMethod>
<DigestValue>TphpTsohWyWK9j+2DXpOyvJSydRMq2Av5B0otjA9f9I=</DigestValue>
</Reference>
<Reference URI="lib%2Ftau%2Fwearable%2Ftheme%2Fdefault%2Fimages%2FPopup%2Ftw_popup_bg_cover.png">
<DigestMethod Algorithm="http://www.w3.org/2001/04/xmlenc#sha256"></DigestMethod>
<DigestValue>vqXi7pK9urSnMFrdVlcc8IFvLcUduAMNIIgbnFvQc4A=</DigestValue>
</Reference>
<Reference URI="lib%2Ftau%2Fwearable%2Ftheme%2Fdefault%2Fimages%2FPopup%2Ftw_toast_popup_bg.png">
<DigestMethod Algorithm="http://www.w3.org/2001/04/xmlenc#sha256"></DigestMethod>
<DigestValue>HQr3u9+djLy7CqBURR3qMnfvWxQRk+7KsyluA9KadzQ=</DigestValue>
</Reference>
<Reference URI="lib%2Ftau%2Fwearable%2Ftheme%2Fdefault%2Fimages%2FPopup%2Ftw_toast_popup_bg_cover.png">
<DigestMethod Algorithm="http://www.w3.org/2001/04/xmlenc#sha256"></DigestMethod>
<DigestValue>PTz1Q9tb2jmV/h/NF704nw/+wpelkdig4FdwBoTkXIs=</DigestValue>
</Reference>
<Reference URI="lib%2Ftau%2Fwearable%2Ftheme%2Fdefault%2Fimages%2FPopup%2Ftw_toast_popup_image_bg.png">
<DigestMethod Algorithm="http://www.w3.org/2001/04/xmlenc#sha256"></DigestMethod>
<DigestValue>3mjrv/wd1wI4zGsbemLKWEA3ARYZyZF/lx8XLE87aSQ=</DigestValue>
</Reference>
<Reference URI="lib%2Ftau%2Fwearable%2Ftheme%2Fdefault%2Fimages%2FPopup%2Ftw_toast_popup_outline.png">
<DigestMethod Algorithm="http://www.w3.org/2001/04/xmlenc#sha256"></DigestMethod>
<DigestValue>mmYqlg9ixS5F00DUDkRiD8LJARxEPw7FwZpsINr4mwU=</DigestValue>
</Reference>
<Reference URI="lib%2Ftau%2Fwearable%2Ftheme%2Fdefault%2Fimages%2FProcessing%2Fprocessingfull.png">
<DigestMethod Algorithm="http://www.w3.org/2001/04/xmlenc#sha256"></DigestMethod>
<DigestValue>inphL/shFiOknwr0eLnUc7CGLICqacQ36GidvhaEuJ4=</DigestValue>
</Reference>
<Reference URI="lib%2Ftau%2Fwearable%2Ftheme%2Fdefault%2Fimages%2FProcessing%2Fprocessingsmall.png">
<DigestMethod Algorithm="http://www.w3.org/2001/04/xmlenc#sha256"></DigestMethod>
<DigestValue>C+hHn6OO+njwAy8GimgFpo+Owigwarpd0+/LdckPdjE=</DigestValue>
</Reference>
<Reference URI="lib%2Ftau%2Fwearable%2Ftheme%2Fdefault%2Fimages%2FScroller%2Fbouncing_bottom_edge.png">
<DigestMethod Algorithm="http://www.w3.org/2001/04/xmlenc#sha256"></DigestMethod>
<DigestValue>EwF0JIrEoFCTVRThWK/aNHTfqUzl+oQ5xaoEVeCKakQ=</DigestValue>
</Reference>
<Reference URI="lib%2Ftau%2Fwearable%2Ftheme%2Fdefault%2Fimages%2FScroller%2Fbouncing_bottom_glow.png">
<DigestMethod Algorithm="http://www.w3.org/2001/04/xmlenc#sha256"></DigestMethod>
<DigestValue>LBBYbeRMyt+BmcaK6OFcYxXCHatfcBy3WZmMEyeD494=</DigestValue>
</Reference>
<Reference URI="lib%2Ftau%2Fwearable%2Ftheme%2Fdefault%2Fimages%2FScroller%2Fbouncing_circle_bottom_edge.png">
<DigestMethod Algorithm="http://www.w3.org/2001/04/xmlenc#sha256"></DigestMethod>
<DigestValue>4zpEk6E15paDUijxsmbabMs46TeXF4D7uOr8yXUBnl0=</DigestValue>
</Reference>
<Reference URI="lib%2Ftau%2Fwearable%2Ftheme%2Fdefault%2Fimages%2FScroller%2Fbouncing_circle_bottom_glow.png">
<DigestMethod Algorithm="http://www.w3.org/2001/04/xmlenc#sha256"></DigestMethod>
<DigestValue>bcGdiIMylFL9ajYUoxh9Z+C/N1yfHdFvrvU4ocYLnoo=</DigestValue>
</Reference>
<Reference URI="lib%2Ftau%2Fwearable%2Ftheme%2Fdefault%2Fimages%2FScroller%2Fbouncing_circle_left_edge.png">
<DigestMethod Algorithm="http://www.w3.org/2001/04/xmlenc#sha256"></DigestMethod>
<DigestValue>IcYY9gteu+cywMJ4ccIK+y8X7RNqxdxY5Xnb2rfW9zg=</DigestValue>
</Reference>
<Reference URI="lib%2Ftau%2Fwearable%2Ftheme%2Fdefault%2Fimages%2FScroller%2Fbouncing_circle_left_glow.png">
<DigestMethod Algorithm="http://www.w3.org/2001/04/xmlenc#sha256"></DigestMethod>
<DigestValue>QJpek9IkYgeOa/DEUu0i+FJYw1G7pud0DErfVy6PtWI=</DigestValue>
</Reference>
<Reference URI="lib%2Ftau%2Fwearable%2Ftheme%2Fdefault%2Fimages%2FScroller%2Fbouncing_circle_right_edge.png">
<DigestMethod Algorithm="http://www.w3.org/2001/04/xmlenc#sha256"></DigestMethod>
<DigestValue>UoL95mMLn9oWwZKXx4xfcKQUd5BZICIiNovQ0X59zpU=</DigestValue>
</Reference>
<Reference URI="lib%2Ftau%2Fwearable%2Ftheme%2Fdefault%2Fimages%2FScroller%2Fbouncing_circle_right_glow.png">
<DigestMethod Algorithm="http://www.w3.org/2001/04/xmlenc#sha256"></DigestMethod>
<DigestValue>5KK+V+kpu/oD6Vd+6gE6JnOnJ29+ZI0ekabrdIX9dXs=</DigestValue>
</Reference>
<Reference URI="lib%2Ftau%2Fwearable%2Ftheme%2Fdefault%2Fimages%2FScroller%2Fbouncing_left_edge.png">
<DigestMethod Algorithm="http://www.w3.org/2001/04/xmlenc#sha256"></DigestMethod>
<DigestValue>ezbad2I+Qvqq+HBtFj5fCR73B7u1OpaGp8LbvJiksx8=</DigestValue>
</Reference>
<Reference URI="lib%2Ftau%2Fwearable%2Ftheme%2Fdefault%2Fimages%2FScroller%2Fbouncing_left_glow.png">
<DigestMethod Algorithm="http://www.w3.org/2001/04/xmlenc#sha256"></DigestMethod>
<DigestValue>i6payEnlv8vWHucju//UBssYNzmr3SES3nSuWDuJU6c=</DigestValue>
</Reference>
<Reference URI="lib%2Ftau%2Fwearable%2Ftheme%2Fdefault%2Fimages%2FScroller%2Fbouncing_right_edge.png">
<DigestMethod Algorithm="http://www.w3.org/2001/04/xmlenc#sha256"></DigestMethod>
<DigestValue>wIF0gTMZq7piBZ9E/+l5UgyW9pSywlBedaETJbK5euE=</DigestValue>
</Reference>
<Reference URI="lib%2Ftau%2Fwearable%2Ftheme%2Fdefault%2Fimages%2FScroller%2Fbouncing_right_glow.png">
<DigestMethod Algorithm="http://www.w3.org/2001/04/xmlenc#sha256"></DigestMethod>
<DigestValue>MZ/WXjPf0eoYefs4grYwm+dI4ehPs1D8ElGWv+wLcGk=</DigestValue>
</Reference>
<Reference URI="lib%2Ftau%2Fwearable%2Ftheme%2Fdefault%2Fimages%2FScroller%2Fbouncing_top_edge.png">
<DigestMethod Algorithm="http://www.w3.org/2001/04/xmlenc#sha256"></DigestMethod>
<DigestValue>iEpyiqHYkrP3GQpul3S6C87yG+PyVBWzhrmvxzPf//0=</DigestValue>
</Reference>
<Reference URI="lib%2Ftau%2Fwearable%2Ftheme%2Fdefault%2Fimages%2FScroller%2Fbouncing_top_glow.png">
<DigestMethod Algorithm="http://www.w3.org/2001/04/xmlenc#sha256"></DigestMethod>
<DigestValue>JmKqm+7nSe0dUkYRduPMoyyfc+Rg9gTVg2J7/pJq5F4=</DigestValue>
</Reference>
<Reference URI="lib%2Ftau%2Fwearable%2Ftheme%2Fdefault%2Fimages%2FSwipelist%2Fb_logs_icon_actionbar_btn_msg_nor.png">
<DigestMethod Algorithm="http://www.w3.org/2001/04/xmlenc#sha256"></DigestMethod>
<DigestValue>f6LUaSBsZsugcSX2A3xcaHs+rghK2nFAneqNp7WbOMw=</DigestValue>
</Reference>
<Reference URI="lib%2Ftau%2Fwearable%2Ftheme%2Fdefault%2Fimages%2FSwipelist%2Fb_logs_icon_body_btn_call_nor.png">
<DigestMethod Algorithm="http://www.w3.org/2001/04/xmlenc#sha256"></DigestMethod>
<DigestValue>fl7TG+5Mgf/y6KR8TdSEPcC/teaTrmRLm+lr9TSpOyg=</DigestValue>
</Reference>
<Reference URI="lib%2Ftau%2Fwearable%2Ftheme%2Fdefault%2Fimages%2FTitle_bar%2Fb_detail_bg_cover.png">
<DigestMethod Algorithm="http://www.w3.org/2001/04/xmlenc#sha256"></DigestMethod>
<DigestValue>6MewTgCyy7oMiEvq3KkLoNcPwf7TXOAoEtF14XSlYoM=</DigestValue>
</Reference>
<Reference URI="lib%2Ftau%2Fwearable%2Ftheme%2Fdefault%2Fimages%2Flistview%2Fb_list_focus_bg.png">
<DigestMethod Algorithm="http://www.w3.org/2001/04/xmlenc#sha256"></DigestMethod>
<DigestValue>Y2mvH98ij+UZgnL50uB1C7O0z7vycVJTo91w7YXqNL8=</DigestValue>
</Reference>
<Reference URI="lib%2Ftau%2Fwearable%2Ftheme%2Fdefault%2Fimages%2Flistview%2Fb_list_focus_bg_ef.png">
<DigestMethod Algorithm="http://www.w3.org/2001/04/xmlenc#sha256"></DigestMethod>
<DigestValue>esp0LccF3OAwLTU/MP0HKKyDwKxOSL+W+r5CkeMRlFs=</DigestValue>
</Reference>
<Reference URI="lib%2Ftau%2Fwearable%2Ftheme%2Fdefault%2Fimages%2Flistview%2Ftw_list_sub_line_left.png">
<DigestMethod Algorithm="http://www.w3.org/2001/04/xmlenc#sha256"></DigestMethod>
<DigestValue>shV08ijW9zUS7nWDPJJhii7sJ+I8PGnaiWIqM2eQupI=</DigestValue>
</Reference>
<Reference URI="lib%2Ftau%2Fwearable%2Ftheme%2Fdefault%2Fimages%2Flistview%2Ftw_list_sub_line_right.png">
<DigestMethod Algorithm="http://www.w3.org/2001/04/xmlenc#sha256"></DigestMethod>
<DigestValue>5bj8yP8hzh1GCTNeAEUIiVshD964KCede5tOIlybtZY=</DigestValue>
</Reference>
<Reference URI="lib%2Ftau%2Fwearable%2Ftheme%2Fdefault%2Ftau.circle.css">
<DigestMethod Algorithm="http://www.w3.org/2001/04/xmlenc#sha256"></DigestMethod>
<DigestValue>frManZad6BQ21GdIQdyuVFJleqSbYhhjeigrvJTYEWo=</DigestValue>
</Reference>
<Reference URI="lib%2Ftau%2Fwearable%2Ftheme%2Fdefault%2Ftau.circle.min.css">
<DigestMethod Algorithm="http://www.w3.org/2001/04/xmlenc#sha256"></DigestMethod>
<DigestValue>/Tmdpl/VCn3Gl/FbOcPJXePOS5shjuVeA8FfClJeLbs=</DigestValue>
</Reference>
<Reference URI="lib%2Ftau%2Fwearable%2Ftheme%2Fdefault%2Ftau.circle.min.template">
<DigestMethod Algorithm="http://www.w3.org/2001/04/xmlenc#sha256"></DigestMethod>
<DigestValue>JTiueoTgaMlzv+qwtryN5WtoTKpsmSTNt7F8Yyzsrwc=</DigestValue>
</Reference>
<Reference URI="lib%2Ftau%2Fwearable%2Ftheme%2Fdefault%2Ftau.circle.template">
<DigestMethod Algorithm="http://www.w3.org/2001/04/xmlenc#sha256"></DigestMethod>
<DigestValue>27zwKy5PHa/D+71uQeYBcffitNUOXlUpJ3uKAV0CTEk=</DigestValue>
</Reference>
<Reference URI="lib%2Ftau%2Fwearable%2Ftheme%2Fdefault%2Ftau.css">
<DigestMethod Algorithm="http://www.w3.org/2001/04/xmlenc#sha256"></DigestMethod>
<DigestValue>TtVuteUo5uSKfc8FyqVEv2u+KeqXKRtfJ1gkPXoyMgI=</DigestValue>
</Reference>
<Reference URI="lib%2Ftau%2Fwearable%2Ftheme%2Fdefault%2Ftau.min.css">
<DigestMethod Algorithm="http://www.w3.org/2001/04/xmlenc#sha256"></DigestMethod>
<DigestValue>nlqraPG4D/iUagIpoBeMNu6hxtPooUhsWr4K83m4tPg=</DigestValue>
</Reference>
<Reference URI="lib%2Ftau%2Fwearable%2Ftheme%2Fdefault%2Ftau.min.template">
<DigestMethod Algorithm="http://www.w3.org/2001/04/xmlenc#sha256"></DigestMethod>
<DigestValue>y4Owv6ufluDCgsH+THhfcqqVvkgxBY8oZshUX51+WxM=</DigestValue>
</Reference>
<Reference URI="lib%2Ftau%2Fwearable%2Ftheme%2Fdefault%2Ftau.template">
<DigestMethod Algorithm="http://www.w3.org/2001/04/xmlenc#sha256"></DigestMethod>
<DigestValue>slIRwwX/GVB+piMwvHdlKEwqa/zzvk9oCvKm00QkC+U=</DigestValue>
</Reference>
<Reference URI="lowBatteryCheck.js">
<DigestMethod Algorithm="http://www.w3.org/2001/04/xmlenc#sha256"></DigestMethod>
<DigestValue>CDpfPYBhkIkZmhuQBOsmQtbwnfEWmjFBRBM47bombHQ=</DigestValue>
</Reference>
<Reference URI="#prop">
<Transforms>
<Transform Algorithm="http://www.w3.org/2006/12/xml-c14n11"></Transform>
</Transforms>
<DigestMethod Algorithm="http://www.w3.org/2001/04/xmlenc#sha256"></DigestMethod>
<DigestValue>u/jU3U4Zm5ihTMSjKGlGYbWzDfRkGphPPHx3gJIYEJ4=</DigestValue>
</Reference>
</SignedInfo>
<SignatureValue>
BDabE35VWPvLMGixrKAEyLTYmrg+ISEivCpccYNcAmbHbTCEH8M/Ot5HPXPy3595LZlnQHD+25Au
3HtCd6Upw+GCsHWLBkSuVOrPl8vREt6IijoQjS7bBgbr/dZ+FeNbGVW4I9702ZhFxXsEAzGLA1Qy
ZJePCjkchMvqMG14Gdk1h9KBoOO8K3DmPvQi5WF1CAgrPB10K+JdZo7Qp88JTb48hNaGOT/cjVgu
RMj/kbekZHiYJ3Ak3tfby2AntbvPAzq/HL6GOkaoJSCm7/KMfz1PuJwytJyaOC8HwsE287cPGI+B
hEKO7x0Yc6GkoizYBbwB7UrEYPzXAe5yYzGMGQ==
</SignatureValue>
<KeyInfo>
<X509Data>
<X509Certificate>
MIIEpTCCA42gAwIBAgIBZTANBgkqhkiG9w0BAQsFADCBnjELMAkGA1UEBhMCS1IxFDASBgNVBAgM
C1NvdXRoIEtvcmVhMQ4wDAYDVQQHDAVTdXdvbjEmMCQGA1UECgwdU2Ftc3VuZyBFbGVjdHJvbmlj
cyBDby4sIEx0ZC4xDzANBgNVBAsMBk1vYmlsZTEwMC4GA1UEAwwnU2Ftc3VuZyBUaXplbiBERVZF
TE9QRVIgUHVibGljIENBIENsYXNzMB4XDTE5MDMxMjA4NDExNFoXDTIwMDMxMTA4NDExNFowggEx
MREwDwYDVQQDDAhUaXplblNESzEJMAcGA1UECwwAMQkwBwYDVQQKDAAxCTAHBgNVBAcMADEJMAcG
A1UECAwAMQkwBwYDVQQGEwAxgeQwgeEGCSqGSIb3DQEJARaB02p1c3RpbmFzQGVvZm5ldC5sdCZz
dGF0ZT1hY2NvdW50Y2hlY2tkb2dlbmVyYXRlZHN0YXRldGV4dCZ0b2tlbl90eXBlPWJlYXJlciZj
bG9zZWRBY3Rpb249c2lnbkluU3VjY2VzcyZ1c2VySWQ9c3hpbzNucm44YyZhY2Nlc3NfdG9rZW5f
ZXhwaXJlc19pbj04NjM5OTQmY2xpZW50X2lkPTRmYjdmbmYzbnAmYXBpX3NlcnZlcl91cmw9dXMt
YXV0aDIuc2Ftc3VuZ29zcC5jb20wggEiMA0GCSqGSIb3DQEBAQUAA4IBDwAwggEKAoIBAQCGDji5
eYxNwCSQQHxFYkawiytUgjxD0REuVLyIubKdYXmQG7QjridOq8G6jk/MO/ruIInHxUOXXpoUg/4D
T28Wa011oXqPw8YtROH2QjlURsjT74dVdjIolVzcF3PVeMOdMIKJssO49PeWDevr5kPUmTkdDdT1
EKRq/KU6LfBiSBaMrxbaAigjyUBmk1VXwHghkgwfEV8xnSuOGB6aGKU0g4Vg2+QgEzzXkCS8s9S7
+QMIrZxiJXEzSLg0tZBOZK8bb9+PB1og1sABjVD39CVXKcwMuTdZA/hEKaYEue1uWyni42d/HocN
UAoc/BEvWFnBuFouasCZcKrq8CYYhpZHAgMBAAGjWDBWMFQGA1UdEQRNMEuGFFVSTjp0aXplbjpw
YWNrYWdlaWQ9hjNVUk46dGl6ZW46ZGV2aWNlaWQ9Mi4wI1dLb0dlWklwVlJFU2pyMGxINXJ2c0V0
S0Nlbz0wDQYJKoZIhvcNAQELBQADggEBABf298HVIZprRB7Wnh7OHYJ67laaJRJyaJtrB/iHGqb/
sdEAfSWYURNugcsyYPZaTZiR8SWaorkkplWolTEmfFspJrfmkk1k2vbu+raQ2XsQf34ICK3gdo2Y
4l6RRIXKiv4hYkEn4kcRGhPMq0Zx/JEyziBY0ZRQH3z+sXHA1SRfDf9O8SfbZpnsSp+1qIeycc+z
AVFxy6rHAsavg85Fd5U4Q46w1JJo44R1Ma7vdrL3sjvsW9X1mMOOnxlveShUATkiQRuu4whKq0/L
9QqJVHRbiQAfcpariDep+Qfzld7EMx/TTvMo1596HPyjCY42RAM1F5hqGBpu045/acLqA4s=
</X509Certificate>
<X509Certificate>
MIIDuzCCAqOgAwIBAgICL+cwDQYJKoZIhvcNAQELBQAwgY8xCzAJBgNVBAYTAktSMRQwEgYDVQQI
DAtTb3V0aCBLb3JlYTEOMAwGA1UEBwwFU3V3b24xJjAkBgNVBAoMHVNhbXN1bmcgRWxlY3Ryb25p
Y3MgQ28uLCBMdGQuMTIwMAYDVQQDDClTYW1zdW5nIFRpemVuIERFVkVMT1BFUiBQdWJsaWMgUm9v
dCBDbGFzczAeFw0xMzEyMzAxNTAxNDdaFw0yODEyMjYxNTAxNDdaMIGeMQswCQYDVQQGEwJLUjEU
MBIGA1UECAwLU291dGggS29yZWExDjAMBgNVBAcMBVN1d29uMSYwJAYDVQQKDB1TYW1zdW5nIEVs
ZWN0cm9uaWNzIENvLiwgTHRkLjEPMA0GA1UECwwGTW9iaWxlMTAwLgYDVQQDDCdTYW1zdW5nIFRp
emVuIERFVkVMT1BFUiBQdWJsaWMgQ0EgQ2xhc3MwggEiMA0GCSqGSIb3DQEBAQUAA4IBDwAwggEK
AoIBAQCkqW9d0zO5NFOc7u164DKe9Yx+yEgUnsbhnJasqHaqT71qaMxyCOjyysZi7gGycDcgmLcU
tr2wSMTGWPibK8SrJ8bV/J1cy9nTpljM3s+lbPIVVxZeufhJkU79tXImHLolERd0vui+rj0Xpd9O
zlyNTRt0+PWVT1taWcbfHL7pUD25hMkTc8C3bC+dUoT1/RhCkXgmUvIor3EnnU0rBtAl4qNtg5y1
7RLT8dyicieAHCcW923YC/ngMZxnBjbL2Ht1RBUvrL6K3X5+l0VeF4qC3g7TKm/a/SGjq12ZD4sc
7rglzjSNlTVSGag6/2WkqxE6HheEBWaloYOdauzwydFNAgMBAAGjEDAOMAwGA1UdEwQFMAMBAf8w
DQYJKoZIhvcNAQELBQADggEBAG88wKjKeTbj5I6wMEvRihd+gWrESJX3bXUSlHWjUfYKcvg3GzM9
cdooscqJdYgN8ezQuYiJQRk7BaPHSlPGkchsPUjvSM6WvIn9IT+VsEuVBrZNbZMSv6lM6wNig3TE
h2OxFTW6Bt8mCZB74EP2wb+39Fr5aJwWvmkxQjct3/O+GYPQhe0Lu1qpbbMhzafYYybSmO+om02V
cTWyJ/vtLUNyGfN7aHyBm6PFE5piAfpBaO9Az+zWil1HOsnzu1tGGnyV6IzQ/UiIo5P2sD8I5lEO
Xdf9Eicy9y5z2Ci2zrmDcAGWL8o5wOWrCqML2ijximFzyQ/swlMC9xBIX9RCFws=
</X509Certificate>
</X509Data>
</KeyInfo>
<Object Id="prop"><SignatureProperties xmlns:dsp="http://www.w3.org/2009/xmldsig-properties"><SignatureProperty Id="profile" Target="#DistributorSignature"><dsp:Profile URI="http://www.w3.org/ns/widgets-digsig#profile"></dsp:Profile></SignatureProperty><SignatureProperty Id="role" Target="#DistributorSignature"><dsp:Role URI="http://www.w3.org/ns/widgets-digsig#role-distributor"></dsp:Role></SignatureProperty><SignatureProperty Id="identifier" Target="#DistributorSignature"><dsp:Identifier></dsp:Identifier></SignatureProperty></SignatureProperties></Object>
</Signature>